{"resultSet":[{"subjectId":"108386","project":"NLST","id":6357385,"modalities":["CT"],"bodyParts":["CHEST"],"species":["337915000"],"timepoints":{},"totalNumberOfStudies":2,"totalNumberOfSeries":11,"studyIdentifiers":[{"seriesIdentifiers":[6424659,6424660,6424661,6424662,6424663,6424664],"seriesAndModality":[],"studyIdentifier":6390509},{"seriesIdentifiers":[6431608,6431609,6431610,6431611,6431612],"seriesAndModality":[],"studyIdentifier":6392740}]},{"subjectId":"108387","project":"NLST","id":12195499,"modalities":["CT"],"bodyParts":["CHEST"],"species":["337915000"],"timepoints":{},"totalNumberOfStudies":3,"totalNumberOfSeries":6,"studyIdentifiers":[{"seriesIdentifiers":[12286852,12286853],"seriesAndModality":[],"studyIdentifier":12233404},{"seriesIdentifiers":[12286908,12286909],"seriesAndModality":[],"studyIdentifier":12233431},{"seriesIdentifiers":[32742771,32742772],"seriesAndModality":[],"studyIdentifier":32704399}]},{"subjectId":"108390","project":"NLST","id":22513343,"modalities":["CT"],"bodyParts":["CHEST"],"species":["337915000"],"timepoints":{},"totalNumberOfStudies":3,"totalNumberOfSeries":9,"studyIdentifiers":[{"seriesIdentifiers":[22585494,22585495,22585496],"seriesAndModality":[],"studyIdentifier":22547874},{"seriesIdentifiers":[22585646,22585647,22585648],"seriesAndModality":[],"studyIdentifier":22547930},{"seriesIdentifiers":[22588000,22588001,22588002],"seriesAndModality":[],"studyIdentifier":22548909}]},{"subjectId":"108391","project":"NLST","id":12192290,"modalities":["CT"],"bodyParts":["CHEST"],"species":["337915000"],"timepoints":{},"totalNumberOfStudies":3,"totalNumberOfSeries":6,"studyIdentifiers":[{"seriesIdentifiers":[12266697,12266698],"seriesAndModality":[],"studyIdentifier":12226635},{"seriesIdentifiers":[12266733,12266734],"seriesAndModality":[],"studyIdentifier":12226653},{"seriesIdentifiers":[22607427,22607428],"seriesAndModality":[],"studyIdentifier":22555747}]},{"subjectId":"108392","project":"NLST","id":32768117,"modalities":["CT"],"bodyParts":["CHEST"],"species":["337915000"],"timepoints":{},"totalNumberOfStudies":3,"totalNumberOfSeries":6,"studyIdentifiers":[{"seriesIdentifiers":[32739210,32739211],"seriesAndModality":[],"studyIdentifier":32703417},{"seriesIdentifiers":[32739248,32739249],"seriesAndModality":[],"studyIdentifier":32703435},{"seriesIdentifiers":[32743457,32743458],"seriesAndModality":[],"studyIdentifier":32704683}]},{"subjectId":"108393","project":"NLST","id":22511953,"modalities":["CT"],"bodyParts":["CHEST"],"species":["337915000"],"timepoints":{},"totalNumberOfStudies":3,"totalNumberOfSeries":9,"studyIdentifiers":[{"seriesIdentifiers":[22578687,22578688,22578689],"seriesAndModality":[],"studyIdentifier":22544978},{"seriesIdentifiers":[22591227,22591228,22591229],"seriesAndModality":[],"studyIdentifier":22550232},{"seriesIdentifiers":[22591309,22591310,22591311],"seriesAndModality":[],"studyIdentifier":22550259}]},{"subjectId":"108395","project":"NLST","id":12195011,"modalities":["CT"],"bodyParts":["CHEST"],"species":["337915000"],"timepoints":{},"totalNumberOfStudies":3,"totalNumberOfSeries":9,"studyIdentifiers":[{"seriesIdentifiers":[12283098,12283099,12283100],"seriesAndModality":[],"studyIdentifier":12232254},{"seriesIdentifiers":[12283113,12283114,12283115],"seriesAndModality":[],"studyIdentifier":12232259},{"seriesIdentifiers":[12284731,12284732,12284733],"seriesAndModality":[],"studyIdentifier":12232804}]},{"subjectId":"108397","project":"NLST","id":9798273,"modalities":["CT"],"bodyParts":["CHEST"],"species":["337915000"],"timepoints":{},"totalNumberOfStudies":3,"totalNumberOfSeries":6,"studyIdentifiers":[{"seriesIdentifiers":[9735528,9735529],"seriesAndModality":[],"studyIdentifier":9766356},{"seriesIdentifiers":[12256208,12256209],"seriesAndModality":[],"studyIdentifier":12222899},{"seriesIdentifiers":[12273691,12273692],"seriesAndModality":[],"studyIdentifier":12229157}]},{"subjectId":"108399","project":"NLST","id":12190634,"modalities":["CT"],"bodyParts":["CHEST"],"species":["337915000"],"timepoints":{},"totalNumberOfStudies":3,"totalNumberOfSeries":9,"studyIdentifiers":[{"seriesIdentifiers":[12258819,12258820,12258821],"seriesAndModality":[],"studyIdentifier":12223707},{"seriesIdentifiers":[12259114,12259115,12259116],"seriesAndModality":[],"studyIdentifier":12223804},{"seriesIdentifiers":[12259252,12259253,12259254],"seriesAndModality":[],"studyIdentifier":12223849}]},{"subjectId":"108400","project":"NLST","id":12195008,"modalities":["CT"],"bodyParts":["CHEST"],"species":["337915000"],"timepoints":{},"totalNumberOfStudies":3,"totalNumberOfSeries":9,"studyIdentifiers":[{"seriesIdentifiers":[12283077,12283078,12283079],"seriesAndModality":[],"studyIdentifier":12232247},{"seriesIdentifiers":[12284728,12284729,12284730],"seriesAndModality":[],"studyIdentifier":12232803},{"seriesIdentifiers":[36845784,36845785,36845786],"seriesAndModality":[],"studyIdentifier":36803711}]},{"subjectId":"108401","project":"NLST","id":12195934,"modalities":["CT"],"bodyParts":["CHEST"],"species":["337915000"],"timepoints":{},"totalNumberOfStudies":3,"totalNumberOfSeries":9,"studyIdentifiers":[{"seriesIdentifiers":[21105274,21105275,21105276],"seriesAndModality":[],"studyIdentifier":12234641},{"seriesIdentifiers":[22577503,22577504,22577505],"seriesAndModality":[],"studyIdentifier":22544533},{"seriesIdentifiers":[22587136,22587137,22587138],"seriesAndModality":[],"studyIdentifier":22548522}]},{"subjectId":"108402","project":"NLST","id":12193324,"modalities":["CT"],"bodyParts":["CHEST"],"species":["337915000"],"timepoints":{},"totalNumberOfStudies":3,"totalNumberOfSeries":8,"studyIdentifiers":[{"seriesIdentifiers":[12272246,12272247,12272248],"seriesAndModality":[],"studyIdentifier":12228606},{"seriesIdentifiers":[21105589,21105590],"seriesAndModality":[],"studyIdentifier":12234758},{"seriesIdentifiers":[41910921,41910922,41910923],"seriesAndModality":[],"studyIdentifier":41877764}]},{"subjectId":"108403","project":"NLST","id":12195368,"modalities":["CT"],"bodyParts":["CHEST"],"species":["337915000"],"timepoints":{},"totalNumberOfStudies":3,"totalNumberOfSeries":9,"studyIdentifiers":[{"seriesIdentifiers":[12285509,12285510,12285511],"seriesAndModality":[],"studyIdentifier":12233074},{"seriesIdentifiers":[36845261,36845262,36845263],"seriesAndModality":[],"studyIdentifier":36803468},{"seriesIdentifiers":[36845836,36845837,36845838],"seriesAndModality":[],"studyIdentifier":36803730}]},{"subjectId":"108405","project":"NLST","id":22511787,"modalities":["CT"],"bodyParts":["CHEST"],"species":["337915000"],"timepoints":{},"totalNumberOfStudies":3,"totalNumberOfSeries":8,"studyIdentifiers":[{"seriesIdentifiers":[22577687,22577688,22577689],"seriesAndModality":[],"studyIdentifier":22544605},{"seriesIdentifiers":[22584583,22584584],"seriesAndModality":[],"studyIdentifier":22547566},{"seriesIdentifiers":[22584675,22584676,22584677],"seriesAndModality":[],"studyIdentifier":22547602}]},{"subjectId":"108407","project":"NLST","id":6357989,"modalities":["CT"],"bodyParts":["CHEST"],"species":["337915000"],"timepoints":{},"totalNumberOfStudies":3,"totalNumberOfSeries":6,"studyIdentifiers":[{"seriesIdentifiers":[6427714,6427715],"seriesAndModality":[],"studyIdentifier":6391591},{"seriesIdentifiers":[9733542,9733543],"seriesAndModality":[],"studyIdentifier":9765462},{"seriesIdentifiers":[31003825,31003826],"seriesAndModality":[],"studyIdentifier":22558912}]},{"subjectId":"108408","project":"NLST","id":12193027,"modalities":["CT"],"bodyParts":["CHEST"],"species":["337915000"],"timepoints":{},"totalNumberOfStudies":3,"totalNumberOfSeries":9,"studyIdentifiers":[{"seriesIdentifiers":[12270814,12270815,12270816],"seriesAndModality":[],"studyIdentifier":12228099},{"seriesIdentifiers":[12270840,12270841,12270842],"seriesAndModality":[],"studyIdentifier":12228108},{"seriesIdentifiers":[22594517,22594518,22594519],"seriesAndModality":[],"studyIdentifier":22551406}]},{"subjectId":"108411","project":"NLST","id":12193000,"modalities":["CT"],"bodyParts":["CHEST"],"species":["337915000"],"timepoints":{},"totalNumberOfStudies":2,"totalNumberOfSeries":6,"studyIdentifiers":[{"seriesIdentifiers":[12270659,12270660,12270661],"seriesAndModality":[],"studyIdentifier":12228046},{"seriesIdentifiers":[22591917,22591918,22591919],"seriesAndModality":[],"studyIdentifier":22550472}]},{"subjectId":"108412","project":"NLST","id":36962761,"modalities":["CT"],"bodyParts":["CHEST"],"species":["337915000"],"timepoints":{},"totalNumberOfStudies":3,"totalNumberOfSeries":8,"studyIdentifiers":[{"seriesIdentifiers":[36842641,36842642,36842643],"seriesAndModality":[],"studyIdentifier":36802296},{"seriesIdentifiers":[36842691,36842692],"seriesAndModality":[],"studyIdentifier":36802314},{"seriesIdentifiers":[36848781,36848782,36848783],"seriesAndModality":[],"studyIdentifier":36804619}]},{"subjectId":"108413","project":"NLST","id":22512993,"modalities":["CT"],"bodyParts":["CHEST"],"species":["337915000"],"timepoints":{},"totalNumberOfStudies":3,"totalNumberOfSeries":10,"studyIdentifiers":[{"seriesIdentifiers":[22583375,22583376,22583377,22583378],"seriesAndModality":[],"studyIdentifier":22547133},{"seriesIdentifiers":[22583457,22583458,22583459],"seriesAndModality":[],"studyIdentifier":22547160},{"seriesIdentifiers":[22600912,22600913,22600914],"seriesAndModality":[],"studyIdentifier":22553764}]},{"subjectId":"108414","project":"NLST","id":22511950,"modalities":["CT"],"bodyParts":["CHEST"],"species":["337915000"],"timepoints":{},"totalNumberOfStudies":3,"totalNumberOfSeries":9,"studyIdentifiers":[{"seriesIdentifiers":[22578678,22578679,22578680],"seriesAndModality":[],"studyIdentifier":22544975},{"seriesIdentifiers":[22591319,22591320,22591321],"seriesAndModality":[],"studyIdentifier":22550262},{"seriesIdentifiers":[22591573,22591574,22591575],"seriesAndModality":[],"studyIdentifier":22550347}]},{"subjectId":"108417","project":"NLST","id":12192777,"modalities":["CT"],"bodyParts":["CHEST"],"species":["337915000"],"timepoints":{},"totalNumberOfStudies":3,"totalNumberOfSeries":6,"studyIdentifiers":[{"seriesIdentifiers":[12269435,12269436],"seriesAndModality":[],"studyIdentifier":12227680},{"seriesIdentifiers":[31004126,31004127],"seriesAndModality":[],"studyIdentifier":22559039},{"seriesIdentifiers":[36840913,36840914],"seriesAndModality":[],"studyIdentifier":36801642}]},{"subjectId":"108418","project":"NLST","id":36962814,"modalities":["CT"],"bodyParts":["CHEST"],"species":["337915000"],"timepoints":{},"totalNumberOfStudies":3,"totalNumberOfSeries":6,"studyIdentifiers":[{"seriesIdentifiers":[36843289,36843290],"seriesAndModality":[],"studyIdentifier":36802540},{"seriesIdentifiers":[36843525,36843526],"seriesAndModality":[],"studyIdentifier":36802656},{"seriesIdentifiers":[36843623,36843624],"seriesAndModality":[],"studyIdentifier":36802705}]},{"subjectId":"108420","project":"NLST","id":35881009,"modalities":["CT"],"bodyParts":["CHEST"],"species":["337915000"],"timepoints":{},"totalNumberOfStudies":2,"totalNumberOfSeries":6,"studyIdentifiers":[{"seriesIdentifiers":[35849587,35849588,35849589],"seriesAndModality":[],"studyIdentifier":35815895},{"seriesIdentifiers":[35849593,35849594,35849595],"seriesAndModality":[],"studyIdentifier":35815897}]},{"subjectId":"108424","project":"NLST","id":22515739,"modalities":["CT"],"bodyParts":["CHEST"],"species":["337915000"],"timepoints":{},"totalNumberOfStudies":3,"totalNumberOfSeries":9,"studyIdentifiers":[{"seriesIdentifiers":[22608093,22608094,22608095],"seriesAndModality":[],"studyIdentifier":22555993},{"seriesIdentifiers":[31003301,31003302,31003303],"seriesAndModality":[],"studyIdentifier":22558733},{"seriesIdentifiers":[31003440,31003441,31003442],"seriesAndModality":[],"studyIdentifier":22558779}]},{"subjectId":"108427","project":"NLST","id":12193649,"modalities":["CT"],"bodyParts":["CHEST"],"species":["337915000"],"timepoints":{},"totalNumberOfStudies":3,"totalNumberOfSeries":9,"studyIdentifiers":[{"seriesIdentifiers":[12274067,12274068,12274069],"seriesAndModality":[],"studyIdentifier":12229296},{"seriesIdentifiers":[22603728,22603729,22603730],"seriesAndModality":[],"studyIdentifier":22554584},{"seriesIdentifiers":[32741500,32741501,32741502],"seriesAndModality":[],"studyIdentifier":32704066}]},{"subjectId":"108429","project":"NLST","id":22514849,"modalities":["CT"],"bodyParts":["CHEST"],"species":["337915000"],"timepoints":{},"totalNumberOfStudies":3,"totalNumberOfSeries":9,"studyIdentifiers":[{"seriesIdentifiers":[22595735,22595736,22595737],"seriesAndModality":[],"studyIdentifier":22551762},{"seriesIdentifiers":[22602653,22602654,22602655],"seriesAndModality":[],"studyIdentifier":22554209},{"seriesIdentifiers":[36835107,36835108,36835109],"seriesAndModality":[],"studyIdentifier":36799615}]},{"subjectId":"108430","project":"NLST","id":12192258,"modalities":["CT"],"bodyParts":["CHEST"],"species":["337915000"],"timepoints":{},"totalNumberOfStudies":3,"totalNumberOfSeries":6,"studyIdentifiers":[{"seriesIdentifiers":[12266579,12266580],"seriesAndModality":[],"studyIdentifier":12226577},{"seriesIdentifiers":[12266850,12266851],"seriesAndModality":[],"studyIdentifier":12226710},{"seriesIdentifiers":[22589789,22589790],"seriesAndModality":[],"studyIdentifier":22549626}]},{"subjectId":"108431","project":"NLST","id":6357993,"modalities":["CT"],"bodyParts":["CHEST"],"species":["337915000"],"timepoints":{},"totalNumberOfStudies":3,"totalNumberOfSeries":6,"studyIdentifiers":[{"seriesIdentifiers":[6427722,6427723],"seriesAndModality":[],"studyIdentifier":6391595},{"seriesIdentifiers":[9735218,9735219],"seriesAndModality":[],"studyIdentifier":9766206},{"seriesIdentifiers":[36847198,36847199],"seriesAndModality":[],"studyIdentifier":36804159}]},{"subjectId":"108432","project":"NLST","id":12193134,"modalities":["CT"],"bodyParts":["CHEST"],"species":["337915000"],"timepoints":{},"totalNumberOfStudies":3,"totalNumberOfSeries":9,"studyIdentifiers":[{"seriesIdentifiers":[12271328,12271329,12271330],"seriesAndModality":[],"studyIdentifier":12228278},{"seriesIdentifiers":[12278696,12278697,12278698],"seriesAndModality":[],"studyIdentifier":12230566},{"seriesIdentifiers":[22602150,22602151,22602152],"seriesAndModality":[],"studyIdentifier":22554024}]},{"subjectId":"108433","project":"NLST","id":22513519,"modalities":["CT"],"bodyParts":["CHEST"],"species":["337915000"],"timepoints":{},"totalNumberOfStudies":3,"totalNumberOfSeries":6,"studyIdentifiers":[{"seriesIdentifiers":[22587341,22587342],"seriesAndModality":[],"studyIdentifier":22548597},{"seriesIdentifiers":[22605903,22605904],"seriesAndModality":[],"studyIdentifier":22555387},{"seriesIdentifiers":[22605915,22605916],"seriesAndModality":[],"studyIdentifier":22555393}]},{"subjectId":"108434","project":"NLST","id":22514334,"modalities":["CT"],"bodyParts":["CHEST"],"species":["337915000"],"timepoints":{},"totalNumberOfStudies":1,"totalNumberOfSeries":3,"studyIdentifiers":[{"seriesIdentifiers":[22592364,22592365,22592366],"seriesAndModality":[],"studyIdentifier":22550622}]},{"subjectId":"108435","project":"NLST","id":22514248,"modalities":["CT"],"bodyParts":["CHEST"],"species":["337915000"],"timepoints":{},"totalNumberOfStudies":3,"totalNumberOfSeries":9,"studyIdentifiers":[{"seriesIdentifiers":[22591546,22591547,22591548],"seriesAndModality":[],"studyIdentifier":22550338},{"seriesIdentifiers":[22591582,22591583,22591584],"seriesAndModality":[],"studyIdentifier":22550350},{"seriesIdentifiers":[22591588,22591589,22591590],"seriesAndModality":[],"studyIdentifier":22550352}]},{"subjectId":"108436","project":"NLST","id":22513811,"modalities":["CT"],"bodyParts":["CHEST"],"species":["337915000"],"timepoints":{},"totalNumberOfStudies":3,"totalNumberOfSeries":5,"studyIdentifiers":[{"seriesIdentifiers":[22589095,22589096],"seriesAndModality":[],"studyIdentifier":22549304},{"seriesIdentifiers":[22590538,22590539],"seriesAndModality":[],"studyIdentifier":22549958},{"seriesIdentifiers":[22590573],"seriesAndModality":[],"studyIdentifier":22549977}]},{"subjectId":"108438","project":"NLST","id":12190278,"modalities":["CT"],"bodyParts":["CHEST"],"species":["337915000"],"timepoints":{},"totalNumberOfStudies":3,"totalNumberOfSeries":9,"studyIdentifiers":[{"seriesIdentifiers":[12257530,12257531,12257532],"seriesAndModality":[],"studyIdentifier":12223252},{"seriesIdentifiers":[12261753,12261754,12261755],"seriesAndModality":[],"studyIdentifier":12224757},{"seriesIdentifiers":[12261778,12261779,12261780],"seriesAndModality":[],"studyIdentifier":12224766}]},{"subjectId":"108439","project":"NLST","id":41844777,"modalities":["CT"],"bodyParts":["CHEST"],"species":["337915000"],"timepoints":{},"totalNumberOfStudies":1,"totalNumberOfSeries":3,"studyIdentifiers":[{"seriesIdentifiers":[41911287,41911288,41911289],"seriesAndModality":[],"studyIdentifier":41877888}]},{"subjectId":"108443","project":"NLST","id":22514856,"modalities":["CT"],"bodyParts":["CHEST"],"species":["337915000"],"timepoints":{},"totalNumberOfStudies":3,"totalNumberOfSeries":9,"studyIdentifiers":[{"seriesIdentifiers":[22595768,22595769,22595770],"seriesAndModality":[],"studyIdentifier":22551773},{"seriesIdentifiers":[22595929,22595930,22595931],"seriesAndModality":[],"studyIdentifier":22551827},{"seriesIdentifiers":[31001456,31001457,31001458],"seriesAndModality":[],"studyIdentifier":22558081}]},{"subjectId":"108444","project":"NLST","id":9798636,"modalities":["CT"],"bodyParts":["CHEST"],"species":["337915000"],"timepoints":{},"totalNumberOfStudies":3,"totalNumberOfSeries":8,"studyIdentifiers":[{"seriesIdentifiers":[9737984,9737985],"seriesAndModality":[],"studyIdentifier":9767450},{"seriesIdentifiers":[32738924,32738925,32738926],"seriesAndModality":[],"studyIdentifier":32703319},{"seriesIdentifiers":[35849790,35849791,35849792],"seriesAndModality":[],"studyIdentifier":35815965}]},{"subjectId":"108447","project":"NLST","id":12195910,"modalities":["CT"],"bodyParts":["CHEST"],"species":["337915000"],"timepoints":{},"totalNumberOfStudies":3,"totalNumberOfSeries":8,"studyIdentifiers":[{"seriesIdentifiers":[21104608,21104609,21104610],"seriesAndModality":[],"studyIdentifier":12234419},{"seriesIdentifiers":[22584077,22584078,22584079],"seriesAndModality":[],"studyIdentifier":22547371},{"seriesIdentifiers":[41910609,41910610],"seriesAndModality":[],"studyIdentifier":41877654}]},{"subjectId":"108448","project":"NLST","id":22512675,"modalities":["CT"],"bodyParts":["CHEST"],"species":["337915000"],"timepoints":{},"totalNumberOfStudies":3,"totalNumberOfSeries":9,"studyIdentifiers":[{"seriesIdentifiers":[22582151,22582152,22582153],"seriesAndModality":[],"studyIdentifier":22546638},{"seriesIdentifiers":[36835138,36835139,36835140],"seriesAndModality":[],"studyIdentifier":36799625},{"seriesIdentifiers":[36837407,36837408,36837409],"seriesAndModality":[],"studyIdentifier":36800591}]},{"subjectId":"108451","project":"NLST","id":22511641,"modalities":["CT"],"bodyParts":["CHEST"],"species":["337915000"],"timepoints":{},"totalNumberOfStudies":3,"totalNumberOfSeries":6,"studyIdentifiers":[{"seriesIdentifiers":[22577203,22577204],"seriesAndModality":[],"studyIdentifier":22544409},{"seriesIdentifiers":[31004265,31004266],"seriesAndModality":[],"studyIdentifier":22559105},{"seriesIdentifiers":[31004322,31004323],"seriesAndModality":[],"studyIdentifier":22559133}]},{"subjectId":"108454","project":"NLST","id":22514390,"modalities":["CT"],"bodyParts":["CHEST"],"species":["337915000"],"timepoints":{},"totalNumberOfStudies":1,"totalNumberOfSeries":3,"studyIdentifiers":[{"seriesIdentifiers":[22592690,22592691,22592692],"seriesAndModality":[],"studyIdentifier":22550737}]},{"subjectId":"108455","project":"NLST","id":22512229,"modalities":["CT"],"bodyParts":["CHEST"],"species":["337915000"],"timepoints":{},"totalNumberOfStudies":3,"totalNumberOfSeries":6,"studyIdentifiers":[{"seriesIdentifiers":[22580006,22580007],"seriesAndModality":[],"studyIdentifier":22545613},{"seriesIdentifiers":[30999203,30999204],"seriesAndModality":[],"studyIdentifier":22557050},{"seriesIdentifiers":[30999630,30999631],"seriesAndModality":[],"studyIdentifier":22557268}]},{"subjectId":"108459","project":"NLST","id":6357884,"modalities":["CT"],"bodyParts":["CHEST"],"species":["337915000"],"timepoints":{},"totalNumberOfStudies":3,"totalNumberOfSeries":8,"studyIdentifiers":[{"seriesIdentifiers":[6427388,6427389],"seriesAndModality":[],"studyIdentifier":6391454},{"seriesIdentifiers":[9738274,9738275,9738276],"seriesAndModality":[],"studyIdentifier":9767575},{"seriesIdentifiers":[9738310,9738311,9738312],"seriesAndModality":[],"studyIdentifier":9767587}]},{"subjectId":"108461","project":"NLST","id":6357986,"modalities":["CT"],"bodyParts":["CHEST"],"species":["337915000"],"timepoints":{},"totalNumberOfStudies":3,"totalNumberOfSeries":6,"studyIdentifiers":[{"seriesIdentifiers":[6427708,6427709],"seriesAndModality":[],"studyIdentifier":6391588},{"seriesIdentifiers":[22600689,22600690],"seriesAndModality":[],"studyIdentifier":22553671},{"seriesIdentifiers":[36847274,36847275],"seriesAndModality":[],"studyIdentifier":36804197}]},{"subjectId":"108465","project":"NLST","id":12191985,"modalities":["CT"],"bodyParts":["CHEST"],"species":["337915000"],"timepoints":{},"totalNumberOfStudies":3,"totalNumberOfSeries":6,"studyIdentifiers":[{"seriesIdentifiers":[12265344,12265345],"seriesAndModality":[],"studyIdentifier":12226046},{"seriesIdentifiers":[12265394,12265395],"seriesAndModality":[],"studyIdentifier":12226071},{"seriesIdentifiers":[12277947,12277948],"seriesAndModality":[],"studyIdentifier":12230313}]},{"subjectId":"108466","project":"NLST","id":22513006,"modalities":["CT"],"bodyParts":["CHEST"],"species":["337915000"],"timepoints":{},"totalNumberOfStudies":3,"totalNumberOfSeries":6,"studyIdentifiers":[{"seriesIdentifiers":[22583580,22583581],"seriesAndModality":[],"studyIdentifier":22547192},{"seriesIdentifiers":[41910334,41910335],"seriesAndModality":[],"studyIdentifier":41877535},{"seriesIdentifiers":[41910448,41910449],"seriesAndModality":[],"studyIdentifier":41877592}]},{"subjectId":"108469","project":"NLST","id":22516131,"modalities":["CT"],"bodyParts":["CHEST"],"species":["337915000"],"timepoints":{},"totalNumberOfStudies":3,"totalNumberOfSeries":6,"studyIdentifiers":[{"seriesIdentifiers":[31000946,31000947],"seriesAndModality":[],"studyIdentifier":22557880},{"seriesIdentifiers":[31000956,31000957],"seriesAndModality":[],"studyIdentifier":22557885},{"seriesIdentifiers":[31000982,31000983],"seriesAndModality":[],"studyIdentifier":22557898}]},{"subjectId":"108470","project":"NLST","id":12191901,"modalities":["CT"],"bodyParts":["CHEST"],"species":["337915000"],"timepoints":{},"totalNumberOfStudies":3,"totalNumberOfSeries":6,"studyIdentifiers":[{"seriesIdentifiers":[12265001,12265002],"seriesAndModality":[],"studyIdentifier":12225876},{"seriesIdentifiers":[12265112,12265113],"seriesAndModality":[],"studyIdentifier":12225931},{"seriesIdentifiers":[36840728,36840729],"seriesAndModality":[],"studyIdentifier":36801565}]},{"subjectId":"108471","project":"NLST","id":3342730,"modalities":["CT"],"bodyParts":["CHEST"],"species":["337915000"],"timepoints":{},"totalNumberOfStudies":3,"totalNumberOfSeries":18,"studyIdentifiers":[{"seriesIdentifiers":[3414374,3414375,3414376,3414377,3414378,3414379],"seriesAndModality":[],"studyIdentifier":3376789},{"seriesIdentifiers":[22601442,22601443,22601444,22601445,22601446,22601447],"seriesAndModality":[],"studyIdentifier":22553871}]},{"subjectId":"108474","project":"NLST","id":9798736,"modalities":["CT"],"bodyParts":["CHEST"],"species":["337915000"],"timepoints":{},"totalNumberOfStudies":3,"totalNumberOfSeries":18,"studyIdentifiers":[{"seriesIdentifiers":[9739219,9739220,9739221,9739222,9739223,9739224],"seriesAndModality":[],"studyIdentifier":9767882},{"seriesIdentifiers":[9739533,9739534,9739535,9739536,9739537,9739538],"seriesAndModality":[],"studyIdentifier":9767937},{"seriesIdentifiers":[36847634,36847635,36847636,36847637,36847638,36847639],"seriesAndModality":[],"studyIdentifier":36804284}]},{"subjectId":"108476","project":"NLST","id":12190133,"modalities":["CT"],"bodyParts":["CHEST"],"species":["337915000"],"timepoints":{},"totalNumberOfStudies":3,"totalNumberOfSeries":17,"studyIdentifiers":[{"seriesIdentifiers":[12256844,12256845,12256846,12256847,12256848],"seriesAndModality":[],"studyIdentifier":12223098},{"seriesIdentifiers":[12262682,12262683,12262684,12262685,12262686,12262687],"seriesAndModality":[],"studyIdentifier":12225084},{"seriesIdentifiers":[12276233,12276234,12276235,12276236,12276237,12276238],"seriesAndModality":[],"studyIdentifier":12229843}]},{"subjectId":"108477","project":"NLST","id":12192492,"modalities":["CT"],"bodyParts":["CHEST"],"species":["337915000"],"timepoints":{},"totalNumberOfStudies":3,"totalNumberOfSeries":9,"studyIdentifiers":[{"seriesIdentifiers":[12268102,12268103,12268104],"seriesAndModality":[],"studyIdentifier":12227214},{"seriesIdentifiers":[12268114,12268115,12268116],"seriesAndModality":[],"studyIdentifier":12227218},{"seriesIdentifiers":[12268117,12268118,12268119],"seriesAndModality":[],"studyIdentifier":12227219}]},{"subjectId":"108478","project":"NLST","id":22515549,"modalities":["CT"],"bodyParts":["CHEST"],"species":["337915000"],"timepoints":{},"totalNumberOfStudies":2,"totalNumberOfSeries":5,"studyIdentifiers":[{"seriesIdentifiers":[22604384,22604385,22604386],"seriesAndModality":[],"studyIdentifier":22554739},{"seriesIdentifiers":[22607816,22607817],"seriesAndModality":[],"studyIdentifier":22555892}]},{"subjectId":"108479","project":"NLST","id":22512437,"modalities":["CT"],"bodyParts":["CHEST"],"species":["337915000"],"timepoints":{},"totalNumberOfStudies":3,"totalNumberOfSeries":6,"studyIdentifiers":[{"seriesIdentifiers":[22581125,22581126],"seriesAndModality":[],"studyIdentifier":22546161},{"seriesIdentifiers":[22581241,22581242],"seriesAndModality":[],"studyIdentifier":22546216},{"seriesIdentifiers":[22581269,22581270],"seriesAndModality":[],"studyIdentifier":22546230}]},{"subjectId":"108482","project":"NLST","id":12193277,"modalities":["CT"],"bodyParts":["CHEST"],"species":["337915000"],"timepoints":{},"totalNumberOfStudies":3,"totalNumberOfSeries":9,"studyIdentifiers":[{"seriesIdentifiers":[12272034,12272035,12272036],"seriesAndModality":[],"studyIdentifier":12228526},{"seriesIdentifiers":[21102661,21102662,21102663],"seriesAndModality":[],"studyIdentifier":12233913},{"seriesIdentifiers":[22584069,22584070,22584071],"seriesAndModality":[],"studyIdentifier":22547368}]},{"subjectId":"108485","project":"NLST","id":12189913,"modalities":["CT"],"bodyParts":["CHEST"],"species":["337915000"],"timepoints":{},"totalNumberOfStudies":2,"totalNumberOfSeries":4,"studyIdentifiers":[{"seriesIdentifiers":[12255865,12255866],"seriesAndModality":[],"studyIdentifier":12222733},{"seriesIdentifiers":[12269286,12269287],"seriesAndModality":[],"studyIdentifier":12227607}]},{"subjectId":"108487","project":"NLST","id":41844745,"modalities":["CT"],"bodyParts":["CHEST"],"species":["337915000"],"timepoints":{},"totalNumberOfStudies":3,"totalNumberOfSeries":6,"studyIdentifiers":[{"seriesIdentifiers":[41910294,41910295],"seriesAndModality":[],"studyIdentifier":41877515},{"seriesIdentifiers":[41910314,41910315],"seriesAndModality":[],"studyIdentifier":41877525},{"seriesIdentifiers":[41910464,41910465],"seriesAndModality":[],"studyIdentifier":41877600}]},{"subjectId":"108488","project":"NLST","id":22515785,"modalities":["CT"],"bodyParts":["CHEST"],"species":["337915000"],"timepoints":{},"totalNumberOfStudies":3,"totalNumberOfSeries":6,"studyIdentifiers":[{"seriesIdentifiers":[22608369,22608370],"seriesAndModality":[],"studyIdentifier":22556113},{"seriesIdentifiers":[22609165,22609166],"seriesAndModality":[],"studyIdentifier":22556493},{"seriesIdentifiers":[31004223,31004224],"seriesAndModality":[],"studyIdentifier":22559084}]},{"subjectId":"108490","project":"NLST","id":36962304,"modalities":["CT"],"bodyParts":["CHEST"],"species":["337915000"],"timepoints":{},"totalNumberOfStudies":3,"totalNumberOfSeries":9,"studyIdentifiers":[{"seriesIdentifiers":[36831239,36831240,36831241],"seriesAndModality":[],"studyIdentifier":36798467},{"seriesIdentifiers":[36836679,36836680,36836681],"seriesAndModality":[],"studyIdentifier":36800289},{"seriesIdentifiers":[36845799,36845800,36845801],"seriesAndModality":[],"studyIdentifier":36803716}]},{"subjectId":"108491","project":"NLST","id":12192560,"modalities":["CT"],"bodyParts":["CHEST"],"species":["337915000"],"timepoints":{},"totalNumberOfStudies":3,"totalNumberOfSeries":18,"studyIdentifiers":[{"seriesIdentifiers":[12268430,12268431,12268432,12268433,12268434],"seriesAndModality":[],"studyIdentifier":12227307},{"seriesIdentifiers":[22604275,22604276,22604277,22604278,22604279,22604280,22604281],"seriesAndModality":[],"studyIdentifier":22554709},{"seriesIdentifiers":[36847580,36847581,36847582,36847583,36847584,36847585],"seriesAndModality":[],"studyIdentifier":36804275}]},{"subjectId":"108493","project":"NLST","id":22512051,"modalities":["CT"],"bodyParts":["CHEST"],"species":["337915000"],"timepoints":{},"totalNumberOfStudies":3,"totalNumberOfSeries":6,"studyIdentifiers":[{"seriesIdentifiers":[22579179,22579180],"seriesAndModality":[],"studyIdentifier":22545207},{"seriesIdentifiers":[36834973,36834974],"seriesAndModality":[],"studyIdentifier":36799564},{"seriesIdentifiers":[36834997,36834998],"seriesAndModality":[],"studyIdentifier":36799576}]},{"subjectId":"108494","project":"NLST","id":36963009,"modalities":["CT"],"bodyParts":["CHEST"],"species":["337915000"],"timepoints":{},"totalNumberOfStudies":2,"totalNumberOfSeries":4,"studyIdentifiers":[{"seriesIdentifiers":[36844448,36844449],"seriesAndModality":[],"studyIdentifier":36803111},{"seriesIdentifiers":[36844522,36844523],"seriesAndModality":[],"studyIdentifier":36803148}]},{"subjectId":"108497","project":"NLST","id":22515387,"modalities":["CT"],"bodyParts":["CHEST"],"species":["337915000"],"timepoints":{},"totalNumberOfStudies":3,"totalNumberOfSeries":9,"studyIdentifiers":[{"seriesIdentifiers":[22602580,22602581,22602582],"seriesAndModality":[],"studyIdentifier":22554185},{"seriesIdentifiers":[36832998,36832999,36833000],"seriesAndModality":[],"studyIdentifier":36799011},{"seriesIdentifiers":[36837797,36837798,36837799],"seriesAndModality":[],"studyIdentifier":36800723}]},{"subjectId":"108499","project":"NLST","id":12193266,"modalities":["CT"],"bodyParts":["CHEST"],"species":["337915000"],"timepoints":{},"totalNumberOfStudies":3,"totalNumberOfSeries":9,"studyIdentifiers":[{"seriesIdentifiers":[12271966,12271967,12271968],"seriesAndModality":[],"studyIdentifier":12228504},{"seriesIdentifiers":[12284496,12284497,12284498],"seriesAndModality":[],"studyIdentifier":12232718},{"seriesIdentifiers":[41910799,41910800,41910801],"seriesAndModality":[],"studyIdentifier":41877723}]},{"subjectId":"108500","project":"NLST","id":12194793,"modalities":["CT"],"bodyParts":["CHEST"],"species":["337915000"],"timepoints":{},"totalNumberOfStudies":3,"totalNumberOfSeries":11,"studyIdentifiers":[{"seriesIdentifiers":[12281709,12281710,12281711],"seriesAndModality":[],"studyIdentifier":12231745},{"seriesIdentifiers":[21104658,21104659,21104660,21104661,21104662],"seriesAndModality":[],"studyIdentifier":12234437},{"seriesIdentifiers":[36848288,36848289,36848290],"seriesAndModality":[],"studyIdentifier":36804448}]},{"subjectId":"108502","project":"NLST","id":3343401,"modalities":["CT"],"bodyParts":["CHEST"],"species":["337915000"],"timepoints":{},"totalNumberOfStudies":2,"totalNumberOfSeries":14,"studyIdentifiers":[{"seriesIdentifiers":[22606828,22606829,22606830,22606831,22606832,22606833],"seriesAndModality":[],"studyIdentifier":22555592}]},{"subjectId":"108504","project":"NLST","id":36962576,"modalities":["CT"],"bodyParts":["CHEST"],"species":["337915000"],"timepoints":{},"totalNumberOfStudies":3,"totalNumberOfSeries":6,"studyIdentifiers":[{"seriesIdentifiers":[36836365,36836366],"seriesAndModality":[],"studyIdentifier":36800134},{"seriesIdentifiers":[36836409,36836410],"seriesAndModality":[],"studyIdentifier":36800156},{"seriesIdentifiers":[36837179,36837180],"seriesAndModality":[],"studyIdentifier":36800493}]},{"subjectId":"108507","project":"NLST","id":6358397,"modalities":["CT"],"bodyParts":["CHEST"],"species":["337915000"],"timepoints":{},"totalNumberOfStudies":3,"totalNumberOfSeries":17,"studyIdentifiers":[{"seriesIdentifiers":[6429934,6429935,6429936,6429937,6429938,6429939],"seriesAndModality":[],"studyIdentifier":6392228},{"seriesIdentifiers":[6430022,6430023,6430024,6430025,6430026],"seriesAndModality":[],"studyIdentifier":6392244},{"seriesIdentifiers":[22601129,22601130,22601131,22601132,22601133,22601134],"seriesAndModality":[],"studyIdentifier":22553816}]},{"subjectId":"108511","project":"NLST","id":6358864,"modalities":["CT"],"bodyParts":["CHEST"],"species":["337915000"],"timepoints":{},"totalNumberOfStudies":3,"totalNumberOfSeries":9,"studyIdentifiers":[{"seriesIdentifiers":[6433572,6433573,6433574],"seriesAndModality":[],"studyIdentifier":6393503},{"seriesIdentifiers":[6433575,6433576,6433577],"seriesAndModality":[],"studyIdentifier":6393504},{"seriesIdentifiers":[12282042,12282043,12282044],"seriesAndModality":[],"studyIdentifier":12231881}]},{"subjectId":"108515","project":"NLST","id":12191345,"modalities":["CT"],"bodyParts":["CHEST"],"species":["337915000"],"timepoints":{},"totalNumberOfStudies":3,"totalNumberOfSeries":9,"studyIdentifiers":[{"seriesIdentifiers":[12262229,12262230,12262231],"seriesAndModality":[],"studyIdentifier":12224925},{"seriesIdentifiers":[12262238,12262239,12262240],"seriesAndModality":[],"studyIdentifier":12224928},{"seriesIdentifiers":[21102749,21102750,21102751],"seriesAndModality":[],"studyIdentifier":12233943}]},{"subjectId":"108519","project":"NLST","id":12191939,"modalities":["CT"],"bodyParts":["CHEST"],"species":["337915000"],"timepoints":{},"totalNumberOfStudies":3,"totalNumberOfSeries":7,"studyIdentifiers":[{"seriesIdentifiers":[12265203,12265204,12265205],"seriesAndModality":[],"studyIdentifier":12225977},{"seriesIdentifiers":[12277963,12277964],"seriesAndModality":[],"studyIdentifier":12230321},{"seriesIdentifiers":[32742935,32742936],"seriesAndModality":[],"studyIdentifier":32704479}]},{"subjectId":"108520","project":"NLST","id":12191143,"modalities":["CT"],"bodyParts":["CHEST"],"species":["337915000"],"timepoints":{},"totalNumberOfStudies":3,"totalNumberOfSeries":6,"studyIdentifiers":[{"seriesIdentifiers":[12261408,12261409],"seriesAndModality":[],"studyIdentifier":12224595},{"seriesIdentifiers":[12261448,12261449],"seriesAndModality":[],"studyIdentifier":12224615},{"seriesIdentifiers":[22605592,22605593],"seriesAndModality":[],"studyIdentifier":22555252}]},{"subjectId":"108525","project":"NLST","id":6357249,"modalities":["CT"],"bodyParts":["CHEST"],"species":["337915000"],"timepoints":{},"totalNumberOfStudies":3,"totalNumberOfSeries":6,"studyIdentifiers":[{"seriesIdentifiers":[6423357,6423358],"seriesAndModality":[],"studyIdentifier":6390153},{"seriesIdentifiers":[22604609,22604610],"seriesAndModality":[],"studyIdentifier":22554818},{"seriesIdentifiers":[31003985,31003986],"seriesAndModality":[],"studyIdentifier":22558974}]},{"subjectId":"108527","project":"NLST","id":12194061,"modalities":["CT"],"bodyParts":["CHEST"],"species":["337915000"],"timepoints":{},"totalNumberOfStudies":3,"totalNumberOfSeries":18,"studyIdentifiers":[{"seriesIdentifiers":[12277009,12277010,12277011,12277012,12277013,12277014],"seriesAndModality":[],"studyIdentifier":12230066},{"seriesIdentifiers":[22606187,22606188,22606189,22606190,22606191,22606192],"seriesAndModality":[],"studyIdentifier":22555479},{"seriesIdentifiers":[35851505,35851506,35851507,35851508,35851509,35851510],"seriesAndModality":[],"studyIdentifier":35816508}]},{"subjectId":"108529","project":"NLST","id":12190715,"modalities":["CT"],"bodyParts":["CHEST"],"species":["337915000"],"timepoints":{},"totalNumberOfStudies":3,"totalNumberOfSeries":9,"studyIdentifiers":[{"seriesIdentifiers":[12259117,12259118,12259119],"seriesAndModality":[],"studyIdentifier":12223805},{"seriesIdentifiers":[12259205,12259206,12259207],"seriesAndModality":[],"studyIdentifier":12223834},{"seriesIdentifiers":[12267789,12267790,12267791],"seriesAndModality":[],"studyIdentifier":12227109}]},{"subjectId":"108533","project":"NLST","id":22516007,"modalities":["CT"],"bodyParts":["CHEST"],"species":["337915000"],"timepoints":{},"totalNumberOfStudies":3,"totalNumberOfSeries":6,"studyIdentifiers":[{"seriesIdentifiers":[30999457,30999458],"seriesAndModality":[],"studyIdentifier":22557183},{"seriesIdentifiers":[30999482,30999483],"seriesAndModality":[],"studyIdentifier":22557195},{"seriesIdentifiers":[30999519,30999520],"seriesAndModality":[],"studyIdentifier":22557213}]},{"subjectId":"108537","project":"NLST","id":6357602,"modalities":["CT"],"bodyParts":["CHEST"],"species":["337915000"],"timepoints":{},"totalNumberOfStudies":3,"totalNumberOfSeries":9,"studyIdentifiers":[{"seriesIdentifiers":[6426100,6426101,6426102],"seriesAndModality":[],"studyIdentifier":6391000},{"seriesIdentifiers":[32738410,32738411,32738412],"seriesAndModality":[],"studyIdentifier":32703171},{"seriesIdentifiers":[32738413,32738414,32738415],"seriesAndModality":[],"studyIdentifier":32703172}]},{"subjectId":"108540","project":"NLST","id":3343172,"modalities":["CT"],"bodyParts":["CHEST"],"species":["337915000"],"timepoints":{},"totalNumberOfStudies":3,"totalNumberOfSeries":16,"studyIdentifiers":[{"seriesIdentifiers":[32741286,32741287,32741288,32741289,32741290],"seriesAndModality":[],"studyIdentifier":32704010}]},{"subjectId":"108542","project":"NLST","id":12192503,"modalities":["CT"],"bodyParts":["CHEST"],"species":["337915000"],"timepoints":{},"totalNumberOfStudies":3,"totalNumberOfSeries":9,"studyIdentifiers":[{"seriesIdentifiers":[12268168,12268169,12268170],"seriesAndModality":[],"studyIdentifier":12227236},{"seriesIdentifiers":[12268174,12268175,12268176],"seriesAndModality":[],"studyIdentifier":12227238},{"seriesIdentifiers":[35849601,35849602,35849603],"seriesAndModality":[],"studyIdentifier":35815900}]},{"subjectId":"108543","project":"NLST","id":22515812,"modalities":["CT"],"bodyParts":["CHEST"],"species":["337915000"],"timepoints":{},"totalNumberOfStudies":1,"totalNumberOfSeries":2,"studyIdentifiers":[{"seriesIdentifiers":[22608488,22608489],"seriesAndModality":[],"studyIdentifier":22556172}]},{"subjectId":"108545","project":"NLST","id":12192016,"modalities":["CT"],"bodyParts":["CHEST"],"species":["337915000"],"timepoints":{},"totalNumberOfStudies":3,"totalNumberOfSeries":6,"studyIdentifiers":[{"seriesIdentifiers":[12265477,12265478],"seriesAndModality":[],"studyIdentifier":12226111},{"seriesIdentifiers":[12266195,12266196],"seriesAndModality":[],"studyIdentifier":12226416},{"seriesIdentifiers":[31004080,31004081],"seriesAndModality":[],"studyIdentifier":22559017}]},{"subjectId":"108547","project":"NLST","id":6357767,"modalities":["CT"],"bodyParts":["CHEST"],"species":["337915000"],"timepoints":{},"totalNumberOfStudies":3,"totalNumberOfSeries":6,"studyIdentifiers":[{"seriesIdentifiers":[6426819,6426820],"seriesAndModality":[],"studyIdentifier":6391200},{"seriesIdentifiers":[9734210,9734211],"seriesAndModality":[],"studyIdentifier":9765754},{"seriesIdentifiers":[12281941,12281942],"seriesAndModality":[],"studyIdentifier":12231845}]},{"subjectId":"108553","project":"NLST","id":12192954,"modalities":["CT"],"bodyParts":["CHEST"],"species":["337915000"],"timepoints":{},"totalNumberOfStudies":3,"totalNumberOfSeries":9,"studyIdentifiers":[{"seriesIdentifiers":[12270391,12270392,12270393],"seriesAndModality":[],"studyIdentifier":12227955},{"seriesIdentifiers":[12270561,12270562,12270563],"seriesAndModality":[],"studyIdentifier":12228013},{"seriesIdentifiers":[21107540,21107541,21107542],"seriesAndModality":[],"studyIdentifier":12235425}]},{"subjectId":"108555","project":"NLST","id":9798592,"modalities":["CT"],"bodyParts":["CHEST"],"species":["337915000"],"timepoints":{},"totalNumberOfStudies":3,"totalNumberOfSeries":8,"studyIdentifiers":[{"seriesIdentifiers":[9737705,9737706],"seriesAndModality":[],"studyIdentifier":9767329},{"seriesIdentifiers":[32738794,32738795,32738796],"seriesAndModality":[],"studyIdentifier":32703276},{"seriesIdentifiers":[32738948,32738949,32738950],"seriesAndModality":[],"studyIdentifier":32703327}]},{"subjectId":"108556","project":"NLST","id":22514152,"modalities":["CT"],"bodyParts":["CHEST"],"species":["337915000"],"timepoints":{},"totalNumberOfStudies":3,"totalNumberOfSeries":9,"studyIdentifiers":[{"seriesIdentifiers":[22590963,22590964,22590965],"seriesAndModality":[],"studyIdentifier":22550131},{"seriesIdentifiers":[22594530,22594531,22594532],"seriesAndModality":[],"studyIdentifier":22551411},{"seriesIdentifiers":[22602665,22602666,22602667],"seriesAndModality":[],"studyIdentifier":22554213}]},{"subjectId":"108557","project":"NLST","id":12191514,"modalities":["CT"],"bodyParts":["CHEST"],"species":["337915000"],"timepoints":{},"totalNumberOfStudies":3,"totalNumberOfSeries":18,"studyIdentifiers":[{"seriesIdentifiers":[12263461,12263462,12263463,12263464,12263465,12263466],"seriesAndModality":[],"studyIdentifier":12225220},{"seriesIdentifiers":[12277241,12277242,12277243,12277244,12277245,12277246],"seriesAndModality":[],"studyIdentifier":12230108},{"seriesIdentifiers":[31003101,31003102,31003103,31003104,31003105,31003106],"seriesAndModality":[],"studyIdentifier":22558693}]},{"subjectId":"108559","project":"NLST","id":36962697,"modalities":["CT"],"bodyParts":["CHEST"],"species":["337915000"],"timepoints":{},"totalNumberOfStudies":3,"totalNumberOfSeries":6,"studyIdentifiers":[{"seriesIdentifiers":[36840784,36840785],"seriesAndModality":[],"studyIdentifier":36801587},{"seriesIdentifiers":[36849131,36849132],"seriesAndModality":[],"studyIdentifier":36804750},{"seriesIdentifiers":[36849258,36849259],"seriesAndModality":[],"studyIdentifier":36804813}]},{"subjectId":"108561","project":"NLST","id":6358086,"modalities":["CT"],"bodyParts":["CHEST"],"species":["337915000"],"timepoints":{},"totalNumberOfStudies":3,"totalNumberOfSeries":6,"studyIdentifiers":[{"seriesIdentifiers":[6427947,6427948],"seriesAndModality":[],"studyIdentifier":6391708},{"seriesIdentifiers":[6428011,6428012],"seriesAndModality":[],"studyIdentifier":6391739},{"seriesIdentifiers":[9733820,9733821],"seriesAndModality":[],"studyIdentifier":9765601}]},{"subjectId":"108562","project":"NLST","id":22511967,"modalities":["CT"],"bodyParts":["CHEST"],"species":["337915000"],"timepoints":{},"totalNumberOfStudies":3,"totalNumberOfSeries":8,"studyIdentifiers":[{"seriesIdentifiers":[22578745,22578746],"seriesAndModality":[],"studyIdentifier":22544999},{"seriesIdentifiers":[22591555,22591556,22591557],"seriesAndModality":[],"studyIdentifier":22550341},{"seriesIdentifiers":[22591612,22591613,22591614],"seriesAndModality":[],"studyIdentifier":22550360}]},{"subjectId":"108567","project":"NLST","id":12194995,"modalities":["CT"],"bodyParts":["CHEST"],"species":["337915000"],"timepoints":{},"totalNumberOfStudies":3,"totalNumberOfSeries":9,"studyIdentifiers":[{"seriesIdentifiers":[12283017,12283018,12283019],"seriesAndModality":[],"studyIdentifier":12232228},{"seriesIdentifiers":[12283044,12283045,12283046],"seriesAndModality":[],"studyIdentifier":12232236},{"seriesIdentifiers":[36849472,36849473,36849474],"seriesAndModality":[],"studyIdentifier":36804897}]},{"subjectId":"108568","project":"NLST","id":22513385,"modalities":["CT"],"bodyParts":["CHEST"],"species":["337915000"],"timepoints":{},"totalNumberOfStudies":3,"totalNumberOfSeries":9,"studyIdentifiers":[{"seriesIdentifiers":[22585679,22585680,22585681],"seriesAndModality":[],"studyIdentifier":22547941},{"seriesIdentifiers":[22588669,22588670,22588671],"seriesAndModality":[],"studyIdentifier":22549161},{"seriesIdentifiers":[22588964,22588965,22588966],"seriesAndModality":[],"studyIdentifier":22549258}]},{"subjectId":"108570","project":"NLST","id":36962690,"modalities":["CT"],"bodyParts":["CHEST"],"species":["337915000"],"timepoints":{},"totalNumberOfStudies":3,"totalNumberOfSeries":6,"studyIdentifiers":[{"seriesIdentifiers":[36840421,36840422],"seriesAndModality":[],"studyIdentifier":36801451},{"seriesIdentifiers":[36840722,36840723],"seriesAndModality":[],"studyIdentifier":36801562},{"seriesIdentifiers":[36840734,36840735],"seriesAndModality":[],"studyIdentifier":36801568}]},{"subjectId":"108574","project":"NLST","id":22514494,"modalities":["CT"],"bodyParts":["CHEST"],"species":["337915000"],"timepoints":{},"totalNumberOfStudies":3,"totalNumberOfSeries":9,"studyIdentifiers":[{"seriesIdentifiers":[22593280,22593281,22593282],"seriesAndModality":[],"studyIdentifier":22550948},{"seriesIdentifiers":[22607276,22607277,22607278],"seriesAndModality":[],"studyIdentifier":22555691},{"seriesIdentifiers":[22607618,22607619,22607620],"seriesAndModality":[],"studyIdentifier":22555819}]},{"subjectId":"108577","project":"NLST","id":6357629,"modalities":["CT"],"bodyParts":["CHEST"],"species":["337915000"],"timepoints":{},"totalNumberOfStudies":3,"totalNumberOfSeries":9,"studyIdentifiers":[{"seriesIdentifiers":[6426187,6426188,6426189],"seriesAndModality":[],"studyIdentifier":6391029},{"seriesIdentifiers":[6431872,6431873,6431874],"seriesAndModality":[],"studyIdentifier":6392822},{"seriesIdentifiers":[6431875,6431876,6431877],"seriesAndModality":[],"studyIdentifier":6392823}]},{"subjectId":"108579","project":"NLST","id":6358620,"modalities":["CT"],"bodyParts":["CHEST"],"species":["337915000"],"timepoints":{},"totalNumberOfStudies":3,"totalNumberOfSeries":6,"studyIdentifiers":[{"seriesIdentifiers":[6432558,6432559],"seriesAndModality":[],"studyIdentifier":6393053},{"seriesIdentifiers":[9733170,9733171],"seriesAndModality":[],"studyIdentifier":9765276},{"seriesIdentifiers":[36841274,36841275],"seriesAndModality":[],"studyIdentifier":36801799}]},{"subjectId":"108580","project":"NLST","id":6358023,"modalities":["CT"],"bodyParts":["CHEST"],"species":["337915000"],"timepoints":{},"totalNumberOfStudies":3,"totalNumberOfSeries":6,"studyIdentifiers":[{"seriesIdentifiers":[6427794,6427795],"seriesAndModality":[],"studyIdentifier":6391631},{"seriesIdentifiers":[9733770,9733771],"seriesAndModality":[],"studyIdentifier":9765576},{"seriesIdentifiers":[36849311,36849312],"seriesAndModality":[],"studyIdentifier":36804839}]},{"subjectId":"108581","project":"NLST","id":22514821,"modalities":["CT"],"bodyParts":["CHEST"],"species":["337915000"],"timepoints":{},"totalNumberOfStudies":3,"totalNumberOfSeries":6,"studyIdentifiers":[{"seriesIdentifiers":[22595618,22595619],"seriesAndModality":[],"studyIdentifier":22551707},{"seriesIdentifiers":[22595651,22595652],"seriesAndModality":[],"studyIdentifier":22551723},{"seriesIdentifiers":[22595674,22595675],"seriesAndModality":[],"studyIdentifier":22551734}]},{"subjectId":"108583","project":"NLST","id":3342739,"modalities":["CT"],"bodyParts":["CHEST"],"species":["337915000"],"timepoints":{},"totalNumberOfStudies":3,"totalNumberOfSeries":17,"studyIdentifiers":[{"seriesIdentifiers":[6424707,6424708,6424709,6424710,6424711,6424712],"seriesAndModality":[],"studyIdentifier":6390517},{"seriesIdentifiers":[36839420,36839421,36839422,36839423,36839424],"seriesAndModality":[],"studyIdentifier":36801242}]},{"subjectId":"108585","project":"NLST","id":9798417,"modalities":["CT"],"bodyParts":["CHEST"],"species":["337915000"],"timepoints":{},"totalNumberOfStudies":3,"totalNumberOfSeries":7,"studyIdentifiers":[{"seriesIdentifiers":[9736250,9736251,9736252],"seriesAndModality":[],"studyIdentifier":9766704},{"seriesIdentifiers":[9738200,9738201],"seriesAndModality":[],"studyIdentifier":9767544},{"seriesIdentifiers":[35848484,35848485],"seriesAndModality":[],"studyIdentifier":35815570}]},{"subjectId":"108586","project":"NLST","id":12194961,"modalities":["CT"],"bodyParts":["CHEST"],"species":["337915000"],"timepoints":{},"totalNumberOfStudies":3,"totalNumberOfSeries":9,"studyIdentifiers":[{"seriesIdentifiers":[12282860,12282861,12282862],"seriesAndModality":[],"studyIdentifier":12232177},{"seriesIdentifiers":[36844785,36844786,36844787],"seriesAndModality":[],"studyIdentifier":36803252},{"seriesIdentifiers":[41911618,41911619,41911620],"seriesAndModality":[],"studyIdentifier":41878036}]}],"totalPatients":25970,"bodyParts":[{"value":"CHEST","count":25970}],"modalities":[{"value":"CT","count":25970}],"collections":[{"value":"NLST","count":25970}],"species":[{"value":"337915000","count":25970}],"maxTimepoints":{},"minTimepoints":{},"sort":"subject-ascending"}