{"resultSet":[{"subjectId":"103061","project":"NLST","id":22513567,"modalities":["CT"],"bodyParts":["CHEST"],"species":["337915000"],"timepoints":{},"totalNumberOfStudies":3,"totalNumberOfSeries":6,"studyIdentifiers":[{"seriesIdentifiers":[22587541,22587542],"seriesAndModality":[],"studyIdentifier":22548694},{"seriesIdentifiers":[22587852,22587853],"seriesAndModality":[],"studyIdentifier":22548844},{"seriesIdentifiers":[22587892,22587893],"seriesAndModality":[],"studyIdentifier":22548863}]},{"subjectId":"103067","project":"NLST","id":9798386,"modalities":["CT"],"bodyParts":["CHEST"],"species":["337915000"],"timepoints":{},"totalNumberOfStudies":3,"totalNumberOfSeries":6,"studyIdentifiers":[{"seriesIdentifiers":[9736083,9736084],"seriesAndModality":[],"studyIdentifier":9766629},{"seriesIdentifiers":[9736139,9736140],"seriesAndModality":[],"studyIdentifier":9766656},{"seriesIdentifiers":[9736149,9736150],"seriesAndModality":[],"studyIdentifier":9766661}]},{"subjectId":"103069","project":"NLST","id":12194755,"modalities":["CT"],"bodyParts":["CHEST"],"species":["337915000"],"timepoints":{},"totalNumberOfStudies":3,"totalNumberOfSeries":9,"studyIdentifiers":[{"seriesIdentifiers":[12281493,12281494,12281495],"seriesAndModality":[],"studyIdentifier":12231677},{"seriesIdentifiers":[21104647,21104648,21104649],"seriesAndModality":[],"studyIdentifier":12234434},{"seriesIdentifiers":[36848315,36848316,36848317],"seriesAndModality":[],"studyIdentifier":36804457}]},{"subjectId":"103073","project":"NLST","id":6357116,"modalities":["CT"],"bodyParts":["CHEST"],"species":["337915000"],"timepoints":{},"totalNumberOfStudies":3,"totalNumberOfSeries":6,"studyIdentifiers":[{"seriesIdentifiers":[6422859,6422860],"seriesAndModality":[],"studyIdentifier":6389904},{"seriesIdentifiers":[6423428,6423429],"seriesAndModality":[],"studyIdentifier":6390188},{"seriesIdentifiers":[9736045,9736046],"seriesAndModality":[],"studyIdentifier":9766610}]},{"subjectId":"103074","project":"NLST","id":12192228,"modalities":["CT"],"bodyParts":["CHEST"],"species":["337915000"],"timepoints":{},"totalNumberOfStudies":3,"totalNumberOfSeries":6,"studyIdentifiers":[{"seriesIdentifiers":[12266451,12266452],"seriesAndModality":[],"studyIdentifier":12226527},{"seriesIdentifiers":[36836076,36836077],"seriesAndModality":[],"studyIdentifier":36800021},{"seriesIdentifiers":[36849149,36849150],"seriesAndModality":[],"studyIdentifier":36804759}]},{"subjectId":"103076","project":"NLST","id":35880994,"modalities":["CT"],"bodyParts":["CHEST"],"species":["337915000"],"timepoints":{},"totalNumberOfStudies":3,"totalNumberOfSeries":6,"studyIdentifiers":[{"seriesIdentifiers":[35849191,35849192],"seriesAndModality":[],"studyIdentifier":35815739},{"seriesIdentifiers":[35849245,35849246],"seriesAndModality":[],"studyIdentifier":35815766},{"seriesIdentifiers":[35849297,35849298],"seriesAndModality":[],"studyIdentifier":35815792}]},{"subjectId":"103078","project":"NLST","id":3343661,"modalities":["CT"],"bodyParts":["CHEST"],"species":["337915000"],"timepoints":{},"totalNumberOfStudies":3,"totalNumberOfSeries":9,"studyIdentifiers":[{"seriesIdentifiers":[32738613,32738614,32738615],"seriesAndModality":[],"studyIdentifier":32703232}]},{"subjectId":"103079","project":"NLST","id":6358482,"modalities":["CT"],"bodyParts":["CHEST"],"species":["337915000"],"timepoints":{},"totalNumberOfStudies":3,"totalNumberOfSeries":9,"studyIdentifiers":[{"seriesIdentifiers":[6430689,6430690,6430691],"seriesAndModality":[],"studyIdentifier":6392483},{"seriesIdentifiers":[6430785,6430786,6430787],"seriesAndModality":[],"studyIdentifier":6392515},{"seriesIdentifiers":[6432482,6432483,6432484],"seriesAndModality":[],"studyIdentifier":6393022}]},{"subjectId":"103084","project":"NLST","id":22515903,"modalities":["CT"],"bodyParts":["CHEST"],"species":["337915000"],"timepoints":{},"totalNumberOfStudies":3,"totalNumberOfSeries":7,"studyIdentifiers":[{"seriesIdentifiers":[22609416],"seriesAndModality":[],"studyIdentifier":22556603},{"seriesIdentifiers":[36833012,36833013,36833014],"seriesAndModality":[],"studyIdentifier":36799015},{"seriesIdentifiers":[36841375,36841376,36841377],"seriesAndModality":[],"studyIdentifier":36801833}]},{"subjectId":"103086","project":"NLST","id":12192348,"modalities":["CT"],"bodyParts":["CHEST"],"species":["337915000"],"timepoints":{},"totalNumberOfStudies":3,"totalNumberOfSeries":10,"studyIdentifiers":[{"seriesIdentifiers":[12267147,12267148],"seriesAndModality":[],"studyIdentifier":12226839},{"seriesIdentifiers":[12267294,12267295],"seriesAndModality":[],"studyIdentifier":12226910},{"seriesIdentifiers":[22597256,22597257,22597258,22597259,22597260,22597261],"seriesAndModality":[],"studyIdentifier":22552246}]},{"subjectId":"103088","project":"NLST","id":22512485,"modalities":["CT"],"bodyParts":["CHEST"],"species":["337915000"],"timepoints":{},"totalNumberOfStudies":3,"totalNumberOfSeries":6,"studyIdentifiers":[{"seriesIdentifiers":[22581271,22581272],"seriesAndModality":[],"studyIdentifier":22546231},{"seriesIdentifiers":[22581288,22581289],"seriesAndModality":[],"studyIdentifier":22546239},{"seriesIdentifiers":[22599883,22599884],"seriesAndModality":[],"studyIdentifier":22553341}]},{"subjectId":"103090","project":"NLST","id":12191819,"modalities":["CT"],"bodyParts":["CHEST"],"species":["337915000"],"timepoints":{},"totalNumberOfStudies":3,"totalNumberOfSeries":6,"studyIdentifiers":[{"seriesIdentifiers":[12264726,12264727],"seriesAndModality":[],"studyIdentifier":12225739},{"seriesIdentifiers":[12264749,12264750],"seriesAndModality":[],"studyIdentifier":12225751},{"seriesIdentifiers":[32742682,32742683],"seriesAndModality":[],"studyIdentifier":32704354}]},{"subjectId":"103093","project":"NLST","id":9797795,"modalities":["CT"],"bodyParts":["CHEST"],"species":["337915000"],"timepoints":{},"totalNumberOfStudies":3,"totalNumberOfSeries":9,"studyIdentifiers":[{"seriesIdentifiers":[9732986,9732987,9732988],"seriesAndModality":[],"studyIdentifier":9765215},{"seriesIdentifiers":[9736216,9736217,9736218],"seriesAndModality":[],"studyIdentifier":9766690},{"seriesIdentifiers":[9736234,9736235,9736236],"seriesAndModality":[],"studyIdentifier":9766696}]},{"subjectId":"103095","project":"NLST","id":12193849,"modalities":["CT"],"bodyParts":["CHEST"],"species":["337915000"],"timepoints":{},"totalNumberOfStudies":3,"totalNumberOfSeries":9,"studyIdentifiers":[{"seriesIdentifiers":[12275134,12275135,12275136],"seriesAndModality":[],"studyIdentifier":12229634},{"seriesIdentifiers":[12280759,12280760,12280761],"seriesAndModality":[],"studyIdentifier":12231410},{"seriesIdentifiers":[32741430,32741431,32741432],"seriesAndModality":[],"studyIdentifier":32704043}]},{"subjectId":"103101","project":"NLST","id":12195981,"modalities":["CT"],"bodyParts":["CHEST"],"species":["337915000"],"timepoints":{},"totalNumberOfStudies":3,"totalNumberOfSeries":9,"studyIdentifiers":[{"seriesIdentifiers":[21105764,21105765,21105766],"seriesAndModality":[],"studyIdentifier":12234826},{"seriesIdentifiers":[36842833,36842834,36842835],"seriesAndModality":[],"studyIdentifier":36802365},{"seriesIdentifiers":[36848808,36848809,36848810],"seriesAndModality":[],"studyIdentifier":36804628}]},{"subjectId":"103103","project":"NLST","id":22512238,"modalities":["CT"],"bodyParts":["CHEST"],"species":["337915000"],"timepoints":{},"totalNumberOfStudies":3,"totalNumberOfSeries":6,"studyIdentifiers":[{"seriesIdentifiers":[22580077,22580078],"seriesAndModality":[],"studyIdentifier":22545648},{"seriesIdentifiers":[22580202,22580203],"seriesAndModality":[],"studyIdentifier":22545709},{"seriesIdentifiers":[22580365,22580366],"seriesAndModality":[],"studyIdentifier":22545789}]},{"subjectId":"103104","project":"NLST","id":22511853,"modalities":["CT"],"bodyParts":["CHEST"],"species":["337915000"],"timepoints":{},"totalNumberOfStudies":3,"totalNumberOfSeries":7,"studyIdentifiers":[{"seriesIdentifiers":[22578076,22578077,22578078],"seriesAndModality":[],"studyIdentifier":22544767},{"seriesIdentifiers":[22578097,22578098],"seriesAndModality":[],"studyIdentifier":22544777},{"seriesIdentifiers":[22578120,22578121],"seriesAndModality":[],"studyIdentifier":22544787}]},{"subjectId":"103106","project":"NLST","id":22515577,"modalities":["CT"],"bodyParts":["CHEST"],"species":["337915000"],"timepoints":{},"totalNumberOfStudies":3,"totalNumberOfSeries":6,"studyIdentifiers":[{"seriesIdentifiers":[22604669,22604670],"seriesAndModality":[],"studyIdentifier":22554848},{"seriesIdentifiers":[22604761,22604762],"seriesAndModality":[],"studyIdentifier":22554893},{"seriesIdentifiers":[31003854,31003855],"seriesAndModality":[],"studyIdentifier":22558926}]},{"subjectId":"103107","project":"NLST","id":12192001,"modalities":["CT"],"bodyParts":["CHEST"],"species":["337915000"],"timepoints":{},"totalNumberOfStudies":3,"totalNumberOfSeries":6,"studyIdentifiers":[{"seriesIdentifiers":[12265436,12265437],"seriesAndModality":[],"studyIdentifier":12226092},{"seriesIdentifiers":[12277929,12277930],"seriesAndModality":[],"studyIdentifier":12230304},{"seriesIdentifiers":[32742921,32742922],"seriesAndModality":[],"studyIdentifier":32704473}]},{"subjectId":"103108","project":"NLST","id":12192064,"modalities":["CT"],"bodyParts":["CHEST"],"species":["337915000"],"timepoints":{},"totalNumberOfStudies":3,"totalNumberOfSeries":9,"studyIdentifiers":[{"seriesIdentifiers":[12265655,12265656,12265657],"seriesAndModality":[],"studyIdentifier":12226180},{"seriesIdentifiers":[12271511,12271512,12271513],"seriesAndModality":[],"studyIdentifier":12228349},{"seriesIdentifiers":[12284677,12284678,12284679],"seriesAndModality":[],"studyIdentifier":12232786}]},{"subjectId":"103109","project":"NLST","id":22514975,"modalities":["CT"],"bodyParts":["CHEST"],"species":["337915000"],"timepoints":{},"totalNumberOfStudies":3,"totalNumberOfSeries":11,"studyIdentifiers":[{"seriesIdentifiers":[22596924,22596925,22596926],"seriesAndModality":[],"studyIdentifier":22552168},{"seriesIdentifiers":[22596942,22596943,22596944],"seriesAndModality":[],"studyIdentifier":22552174},{"seriesIdentifiers":[22596981,22596982,22596983,22596984,22596985],"seriesAndModality":[],"studyIdentifier":22552187}]},{"subjectId":"103112","project":"NLST","id":12195902,"modalities":["CT"],"bodyParts":["CHEST"],"species":["337915000"],"timepoints":{},"totalNumberOfStudies":3,"totalNumberOfSeries":7,"studyIdentifiers":[{"seriesIdentifiers":[21104546,21104547,21104548],"seriesAndModality":[],"studyIdentifier":12234395},{"seriesIdentifiers":[21106701,21106702],"seriesAndModality":[],"studyIdentifier":12235145},{"seriesIdentifiers":[36838751,36838752],"seriesAndModality":[],"studyIdentifier":36801044}]},{"subjectId":"103114","project":"NLST","id":3343680,"modalities":["CT"],"bodyParts":["CHEST"],"species":["337915000"],"timepoints":{},"totalNumberOfStudies":3,"totalNumberOfSeries":8,"studyIdentifiers":[{"seriesIdentifiers":[6424064,6424065],"seriesAndModality":[],"studyIdentifier":6390365},{"seriesIdentifiers":[6431622,6431623,6431624],"seriesAndModality":[],"studyIdentifier":6392743}]},{"subjectId":"103115","project":"NLST","id":12196007,"modalities":["CT"],"bodyParts":["CHEST"],"species":["337915000"],"timepoints":{},"totalNumberOfStudies":3,"totalNumberOfSeries":8,"studyIdentifiers":[{"seriesIdentifiers":[21106225,21106226,21106227],"seriesAndModality":[],"studyIdentifier":12234981},{"seriesIdentifiers":[21106244,21106245],"seriesAndModality":[],"studyIdentifier":12234989},{"seriesIdentifiers":[22600367,22600368,22600369],"seriesAndModality":[],"studyIdentifier":22553557}]},{"subjectId":"103116","project":"NLST","id":12190829,"modalities":["CT"],"bodyParts":["CHEST"],"species":["337915000"],"timepoints":{},"totalNumberOfStudies":3,"totalNumberOfSeries":9,"studyIdentifiers":[{"seriesIdentifiers":[12259795,12259796,12259797],"seriesAndModality":[],"studyIdentifier":12224033},{"seriesIdentifiers":[12266941,12266942,12266943],"seriesAndModality":[],"studyIdentifier":12226751},{"seriesIdentifiers":[12266984,12266985,12266986],"seriesAndModality":[],"studyIdentifier":12226766}]},{"subjectId":"103120","project":"NLST","id":3342962,"modalities":["CT"],"bodyParts":["CHEST"],"species":["337915000"],"timepoints":{},"totalNumberOfStudies":3,"totalNumberOfSeries":15,"studyIdentifiers":[{"seriesIdentifiers":[32735537,32735538,32735539,32735540,32735541],"seriesAndModality":[],"studyIdentifier":32702518}]},{"subjectId":"103121","project":"NLST","id":3342899,"modalities":["CT"],"bodyParts":["CHEST"],"species":["337915000"],"timepoints":{},"totalNumberOfStudies":3,"totalNumberOfSeries":9,"studyIdentifiers":[{"seriesIdentifiers":[6430591,6430592,6430593],"seriesAndModality":[],"studyIdentifier":6392443}]},{"subjectId":"103122","project":"NLST","id":3343615,"modalities":["CT"],"bodyParts":["CHEST"],"species":["337915000"],"timepoints":{},"totalNumberOfStudies":3,"totalNumberOfSeries":18,"studyIdentifiers":[{"seriesIdentifiers":[32741065,32741066,32741067,32741068,32741069,32741070],"seriesAndModality":[],"studyIdentifier":32703971}]},{"subjectId":"103123","project":"NLST","id":6357727,"modalities":["CT"],"bodyParts":["CHEST"],"species":["337915000"],"timepoints":{},"totalNumberOfStudies":3,"totalNumberOfSeries":19,"studyIdentifiers":[{"seriesIdentifiers":[6426685,6426686,6426687,6426688,6426689,6426690,6426691],"seriesAndModality":[],"studyIdentifier":6391160},{"seriesIdentifiers":[6429127,6429128,6429129,6429130,6429131,6429132],"seriesAndModality":[],"studyIdentifier":6392091},{"seriesIdentifiers":[32740733,32740734,32740735,32740736,32740737,32740738],"seriesAndModality":[],"studyIdentifier":32703911}]},{"subjectId":"103125","project":"NLST","id":22516243,"modalities":["CT"],"bodyParts":["CHEST"],"species":["337915000"],"timepoints":{},"totalNumberOfStudies":3,"totalNumberOfSeries":9,"studyIdentifiers":[{"seriesIdentifiers":[31002549,31002550,31002551],"seriesAndModality":[],"studyIdentifier":22558477},{"seriesIdentifiers":[32743616,32743617,32743618],"seriesAndModality":[],"studyIdentifier":32704737},{"seriesIdentifiers":[32743619,32743620,32743621],"seriesAndModality":[],"studyIdentifier":32704738}]},{"subjectId":"103128","project":"NLST","id":6357121,"modalities":["CT"],"bodyParts":["CHEST"],"species":["337915000"],"timepoints":{},"totalNumberOfStudies":3,"totalNumberOfSeries":6,"studyIdentifiers":[{"seriesIdentifiers":[6422869,6422870],"seriesAndModality":[],"studyIdentifier":6389909},{"seriesIdentifiers":[6423285,6423286],"seriesAndModality":[],"studyIdentifier":6390117},{"seriesIdentifiers":[36832897,36832898],"seriesAndModality":[],"studyIdentifier":36798970}]},{"subjectId":"103129","project":"NLST","id":32768123,"modalities":["CT"],"bodyParts":["CHEST"],"species":["337915000"],"timepoints":{},"totalNumberOfStudies":3,"totalNumberOfSeries":7,"studyIdentifiers":[{"seriesIdentifiers":[32739262,32739263],"seriesAndModality":[],"studyIdentifier":32703441},{"seriesIdentifiers":[32739272,32739273],"seriesAndModality":[],"studyIdentifier":32703446},{"seriesIdentifiers":[32739390,32739391,32739392],"seriesAndModality":[],"studyIdentifier":32703505}]},{"subjectId":"103131","project":"NLST","id":22514009,"modalities":["CT"],"bodyParts":["CHEST"],"species":["337915000"],"timepoints":{},"totalNumberOfStudies":2,"totalNumberOfSeries":5,"studyIdentifiers":[{"seriesIdentifiers":[22590088,22590089],"seriesAndModality":[],"studyIdentifier":22549748},{"seriesIdentifiers":[22595292,22595293,22595294],"seriesAndModality":[],"studyIdentifier":22551550}]},{"subjectId":"103132","project":"NLST","id":12194314,"modalities":["CT"],"bodyParts":["CHEST"],"species":["337915000"],"timepoints":{},"totalNumberOfStudies":3,"totalNumberOfSeries":6,"studyIdentifiers":[{"seriesIdentifiers":[12279188,12279189],"seriesAndModality":[],"studyIdentifier":12230750},{"seriesIdentifiers":[22600729,22600730],"seriesAndModality":[],"studyIdentifier":22553685},{"seriesIdentifiers":[22600735,22600736],"seriesAndModality":[],"studyIdentifier":22553688}]},{"subjectId":"103133","project":"NLST","id":6357735,"modalities":["CT"],"bodyParts":["CHEST"],"species":["337915000"],"timepoints":{},"totalNumberOfStudies":3,"totalNumberOfSeries":17,"studyIdentifiers":[{"seriesIdentifiers":[6426734,6426735,6426736,6426737,6426738,6426739],"seriesAndModality":[],"studyIdentifier":6391168},{"seriesIdentifiers":[6429395,6429396,6429397,6429398,6429399,6429400],"seriesAndModality":[],"studyIdentifier":6392136},{"seriesIdentifiers":[22601059,22601060,22601061,22601062,22601063],"seriesAndModality":[],"studyIdentifier":22553802}]},{"subjectId":"103135","project":"NLST","id":9798281,"modalities":["CT"],"bodyParts":["CHEST"],"species":["337915000"],"timepoints":{},"totalNumberOfStudies":3,"totalNumberOfSeries":7,"studyIdentifiers":[{"seriesIdentifiers":[9735560,9735561,9735562],"seriesAndModality":[],"studyIdentifier":9766372},{"seriesIdentifiers":[9735610,9735611],"seriesAndModality":[],"studyIdentifier":9766394},{"seriesIdentifiers":[36832819,36832820],"seriesAndModality":[],"studyIdentifier":36798934}]},{"subjectId":"103136","project":"NLST","id":6358192,"modalities":["CT"],"bodyParts":["CHEST"],"species":["337915000"],"timepoints":{},"totalNumberOfStudies":3,"totalNumberOfSeries":5,"studyIdentifiers":[{"seriesIdentifiers":[6428267],"seriesAndModality":[],"studyIdentifier":6391866},{"seriesIdentifiers":[31000853,31000854],"seriesAndModality":[],"studyIdentifier":22557832},{"seriesIdentifiers":[31000868,31000869],"seriesAndModality":[],"studyIdentifier":22557840}]},{"subjectId":"103137","project":"NLST","id":22515278,"modalities":["CT"],"bodyParts":["CHEST"],"species":["337915000"],"timepoints":{},"totalNumberOfStudies":1,"totalNumberOfSeries":3,"studyIdentifiers":[{"seriesIdentifiers":[22600413,22600414,22600415],"seriesAndModality":[],"studyIdentifier":22553576}]},{"subjectId":"103138","project":"NLST","id":32768218,"modalities":["CT"],"bodyParts":["CHEST"],"species":["337915000"],"timepoints":{},"totalNumberOfStudies":2,"totalNumberOfSeries":4,"studyIdentifiers":[{"seriesIdentifiers":[32742973,32742974],"seriesAndModality":[],"studyIdentifier":32704498},{"seriesIdentifiers":[32743153,32743154],"seriesAndModality":[],"studyIdentifier":32704588}]},{"subjectId":"103141","project":"NLST","id":3343569,"modalities":["CT"],"bodyParts":["CHEST"],"species":["337915000"],"timepoints":{},"totalNumberOfStudies":3,"totalNumberOfSeries":15,"studyIdentifiers":[{"seriesIdentifiers":[36839568,36839569,36839570,36839571,36839572],"seriesAndModality":[],"studyIdentifier":36801267}]},{"subjectId":"103142","project":"NLST","id":22512465,"modalities":["CT"],"bodyParts":["CHEST"],"species":["337915000"],"timepoints":{},"totalNumberOfStudies":3,"totalNumberOfSeries":8,"studyIdentifiers":[{"seriesIdentifiers":[22581186,22581187,22581188,22581189],"seriesAndModality":[],"studyIdentifier":22546190},{"seriesIdentifiers":[22586980,22586981],"seriesAndModality":[],"studyIdentifier":22548448},{"seriesIdentifiers":[30999044,30999045],"seriesAndModality":[],"studyIdentifier":22556971}]},{"subjectId":"103145","project":"NLST","id":22514461,"modalities":["CT"],"bodyParts":["CHEST"],"species":["337915000"],"timepoints":{},"totalNumberOfStudies":3,"totalNumberOfSeries":7,"studyIdentifiers":[{"seriesIdentifiers":[22593102,22593103,22593104],"seriesAndModality":[],"studyIdentifier":22550872},{"seriesIdentifiers":[22593124,22593125],"seriesAndModality":[],"studyIdentifier":22550882},{"seriesIdentifiers":[22593138,22593139],"seriesAndModality":[],"studyIdentifier":22550889}]},{"subjectId":"103146","project":"NLST","id":9798024,"modalities":["CT"],"bodyParts":["CHEST"],"species":["337915000"],"timepoints":{},"totalNumberOfStudies":1,"totalNumberOfSeries":2,"studyIdentifiers":[{"seriesIdentifiers":[9734496,9734497],"seriesAndModality":[],"studyIdentifier":9765867}]},{"subjectId":"103147","project":"NLST","id":22511890,"modalities":["CT"],"bodyParts":["CHEST"],"species":["337915000"],"timepoints":{},"totalNumberOfStudies":3,"totalNumberOfSeries":9,"studyIdentifiers":[{"seriesIdentifiers":[22578376,22578377,22578378],"seriesAndModality":[],"studyIdentifier":22544868},{"seriesIdentifiers":[22590990,22590991,22590992],"seriesAndModality":[],"studyIdentifier":22550140},{"seriesIdentifiers":[22594453,22594454,22594455],"seriesAndModality":[],"studyIdentifier":22551386}]},{"subjectId":"103149","project":"NLST","id":12195519,"modalities":["CT"],"bodyParts":["CHEST"],"species":["337915000"],"timepoints":{},"totalNumberOfStudies":3,"totalNumberOfSeries":6,"studyIdentifiers":[{"seriesIdentifiers":[12286902,12286903],"seriesAndModality":[],"studyIdentifier":12233428},{"seriesIdentifiers":[12286924,12286925],"seriesAndModality":[],"studyIdentifier":12233439},{"seriesIdentifiers":[32742811,32742812],"seriesAndModality":[],"studyIdentifier":32704419}]},{"subjectId":"103150","project":"NLST","id":32768105,"modalities":["CT"],"bodyParts":["CHEST"],"species":["337915000"],"timepoints":{},"totalNumberOfStudies":3,"totalNumberOfSeries":9,"studyIdentifiers":[{"seriesIdentifiers":[32738473,32738474,32738475],"seriesAndModality":[],"studyIdentifier":32703192},{"seriesIdentifiers":[32738476,32738477,32738478],"seriesAndModality":[],"studyIdentifier":32703193},{"seriesIdentifiers":[32738479,32738480,32738481],"seriesAndModality":[],"studyIdentifier":32703194}]},{"subjectId":"103151","project":"NLST","id":36962397,"modalities":["CT"],"bodyParts":["CHEST"],"species":["337915000"],"timepoints":{},"totalNumberOfStudies":1,"totalNumberOfSeries":5,"studyIdentifiers":[{"seriesIdentifiers":[36832747,36832748,36832749,36832750,36832751],"seriesAndModality":[],"studyIdentifier":36798908}]},{"subjectId":"103152","project":"NLST","id":12195291,"modalities":["CT"],"bodyParts":["CHEST"],"species":["337915000"],"timepoints":{},"totalNumberOfStudies":3,"totalNumberOfSeries":9,"studyIdentifiers":[{"seriesIdentifiers":[12284898,12284899,12284900],"seriesAndModality":[],"studyIdentifier":12232859},{"seriesIdentifiers":[12285137,12285138,12285139],"seriesAndModality":[],"studyIdentifier":12232939},{"seriesIdentifiers":[36835884,36835885,36835886],"seriesAndModality":[],"studyIdentifier":36799957}]},{"subjectId":"103153","project":"NLST","id":6357348,"modalities":["CT"],"bodyParts":["CHEST"],"species":["337915000"],"timepoints":{},"totalNumberOfStudies":3,"totalNumberOfSeries":9,"studyIdentifiers":[{"seriesIdentifiers":[6424384,6424385,6424386],"seriesAndModality":[],"studyIdentifier":6390448},{"seriesIdentifiers":[6431800,6431801,6431802],"seriesAndModality":[],"studyIdentifier":6392799},{"seriesIdentifiers":[6431806,6431807,6431808],"seriesAndModality":[],"studyIdentifier":6392801}]},{"subjectId":"103155","project":"NLST","id":12192069,"modalities":["CT"],"bodyParts":["CHEST"],"species":["337915000"],"timepoints":{},"totalNumberOfStudies":3,"totalNumberOfSeries":9,"studyIdentifiers":[{"seriesIdentifiers":[12265670,12265671,12265672],"seriesAndModality":[],"studyIdentifier":12226185},{"seriesIdentifiers":[12268908,12268909,12268910],"seriesAndModality":[],"studyIdentifier":12227462},{"seriesIdentifiers":[31003746,31003747,31003748],"seriesAndModality":[],"studyIdentifier":22558882}]},{"subjectId":"103156","project":"NLST","id":22512762,"modalities":["CT"],"bodyParts":["CHEST"],"species":["337915000"],"timepoints":{},"totalNumberOfStudies":3,"totalNumberOfSeries":6,"studyIdentifiers":[{"seriesIdentifiers":[22582463,22582464],"seriesAndModality":[],"studyIdentifier":22546758},{"seriesIdentifiers":[22586694,22586695],"seriesAndModality":[],"studyIdentifier":22548308},{"seriesIdentifiers":[22586710,22586711],"seriesAndModality":[],"studyIdentifier":22548316}]},{"subjectId":"103163","project":"NLST","id":6358429,"modalities":["CT"],"bodyParts":["CHEST"],"species":["337915000"],"timepoints":{},"totalNumberOfStudies":2,"totalNumberOfSeries":3,"studyIdentifiers":[{"seriesIdentifiers":[6430240,6430241],"seriesAndModality":[],"studyIdentifier":6392320},{"seriesIdentifiers":[6430367],"seriesAndModality":[],"studyIdentifier":6392366}]},{"subjectId":"103164","project":"NLST","id":12189708,"modalities":["CT"],"bodyParts":["CHEST"],"species":["337915000"],"timepoints":{},"totalNumberOfStudies":3,"totalNumberOfSeries":9,"studyIdentifiers":[{"seriesIdentifiers":[12255272,12255273,12255274],"seriesAndModality":[],"studyIdentifier":12222478},{"seriesIdentifiers":[12274992,12274993,12274994],"seriesAndModality":[],"studyIdentifier":12229587},{"seriesIdentifiers":[12278607,12278608,12278609],"seriesAndModality":[],"studyIdentifier":12230536}]},{"subjectId":"103167","project":"NLST","id":9797642,"modalities":["CT"],"bodyParts":["CHEST"],"species":["337915000"],"timepoints":{},"totalNumberOfStudies":3,"totalNumberOfSeries":9,"studyIdentifiers":[{"seriesIdentifiers":[9732195,9732196,9732197],"seriesAndModality":[],"studyIdentifier":9764902},{"seriesIdentifiers":[9732249,9732250,9732251],"seriesAndModality":[],"studyIdentifier":9764920},{"seriesIdentifiers":[9732279,9732280,9732281],"seriesAndModality":[],"studyIdentifier":9764930}]},{"subjectId":"103168","project":"NLST","id":12190813,"modalities":["CT"],"bodyParts":["CHEST"],"species":["337915000"],"timepoints":{},"totalNumberOfStudies":3,"totalNumberOfSeries":8,"studyIdentifiers":[{"seriesIdentifiers":[12259706,12259707,12259708],"seriesAndModality":[],"studyIdentifier":12224004},{"seriesIdentifiers":[12261169,12261170,12261171],"seriesAndModality":[],"studyIdentifier":12224493},{"seriesIdentifiers":[12266935,12266936],"seriesAndModality":[],"studyIdentifier":12226748}]},{"subjectId":"103169","project":"NLST","id":12194947,"modalities":["CT"],"bodyParts":["CHEST"],"species":["337915000"],"timepoints":{},"totalNumberOfStudies":3,"totalNumberOfSeries":9,"studyIdentifiers":[{"seriesIdentifiers":[12282788,12282789,12282790],"seriesAndModality":[],"studyIdentifier":12232153},{"seriesIdentifiers":[12282925,12282926,12282927],"seriesAndModality":[],"studyIdentifier":12232198},{"seriesIdentifiers":[12283527,12283528,12283529],"seriesAndModality":[],"studyIdentifier":12232395}]},{"subjectId":"103174","project":"NLST","id":36963127,"modalities":["CT"],"bodyParts":["CHEST"],"species":["337915000"],"timepoints":{},"totalNumberOfStudies":2,"totalNumberOfSeries":4,"studyIdentifiers":[{"seriesIdentifiers":[36849742,36849743],"seriesAndModality":[],"studyIdentifier":36805013},{"seriesIdentifiers":[36849754,36849755],"seriesAndModality":[],"studyIdentifier":36805019}]},{"subjectId":"103175","project":"NLST","id":22514960,"modalities":["CT"],"bodyParts":["CHEST"],"species":["337915000"],"timepoints":{},"totalNumberOfStudies":3,"totalNumberOfSeries":7,"studyIdentifiers":[{"seriesIdentifiers":[22596770,22596771,22596772],"seriesAndModality":[],"studyIdentifier":22552117},{"seriesIdentifiers":[36842556,36842557],"seriesAndModality":[],"studyIdentifier":36802256},{"seriesIdentifiers":[36842592,36842593],"seriesAndModality":[],"studyIdentifier":36802273}]},{"subjectId":"103176","project":"NLST","id":12191551,"modalities":["CT"],"bodyParts":["CHEST"],"species":["337915000"],"timepoints":{},"totalNumberOfStudies":3,"totalNumberOfSeries":6,"studyIdentifiers":[{"seriesIdentifiers":[12263613,12263614],"seriesAndModality":[],"studyIdentifier":12225257},{"seriesIdentifiers":[12263645,12263646],"seriesAndModality":[],"studyIdentifier":12225275},{"seriesIdentifiers":[12263668,12263669],"seriesAndModality":[],"studyIdentifier":12225288}]},{"subjectId":"103178","project":"NLST","id":3342411,"modalities":["CT"],"bodyParts":["CHEST"],"species":["337915000"],"timepoints":{},"totalNumberOfStudies":3,"totalNumberOfSeries":8,"studyIdentifiers":[{"seriesIdentifiers":[9736662,9736663],"seriesAndModality":[],"studyIdentifier":9766876},{"seriesIdentifiers":[22600599,22600600,22600601],"seriesAndModality":[],"studyIdentifier":22553639}]},{"subjectId":"103181","project":"NLST","id":22512069,"modalities":["CT"],"bodyParts":["CHEST"],"species":["337915000"],"timepoints":{},"totalNumberOfStudies":3,"totalNumberOfSeries":6,"studyIdentifiers":[{"seriesIdentifiers":[22579268,22579269],"seriesAndModality":[],"studyIdentifier":22545251},{"seriesIdentifiers":[22579738,22579739],"seriesAndModality":[],"studyIdentifier":22545481},{"seriesIdentifiers":[22579858,22579859],"seriesAndModality":[],"studyIdentifier":22545540}]},{"subjectId":"103182","project":"NLST","id":12195283,"modalities":["CT"],"bodyParts":["CHEST"],"species":["337915000"],"timepoints":{},"totalNumberOfStudies":3,"totalNumberOfSeries":9,"studyIdentifiers":[{"seriesIdentifiers":[12284796,12284797,12284798],"seriesAndModality":[],"studyIdentifier":12232826},{"seriesIdentifiers":[31003731,31003732,31003733],"seriesAndModality":[],"studyIdentifier":22558877},{"seriesIdentifiers":[36848950,36848951,36848952],"seriesAndModality":[],"studyIdentifier":36804680}]},{"subjectId":"103184","project":"NLST","id":32768107,"modalities":["CT"],"bodyParts":["CHEST"],"species":["337915000"],"timepoints":{},"totalNumberOfStudies":3,"totalNumberOfSeries":9,"studyIdentifiers":[{"seriesIdentifiers":[32738515,32738516,32738517],"seriesAndModality":[],"studyIdentifier":32703206},{"seriesIdentifiers":[32738518,32738519,32738520],"seriesAndModality":[],"studyIdentifier":32703207},{"seriesIdentifiers":[32738521,32738522,32738523],"seriesAndModality":[],"studyIdentifier":32703208}]},{"subjectId":"103188","project":"NLST","id":12194968,"modalities":["CT"],"bodyParts":["CHEST"],"species":["337915000"],"timepoints":{},"totalNumberOfStudies":3,"totalNumberOfSeries":9,"studyIdentifiers":[{"seriesIdentifiers":[12282895,12282896,12282897],"seriesAndModality":[],"studyIdentifier":12232188},{"seriesIdentifiers":[36836188,36836189,36836190],"seriesAndModality":[],"studyIdentifier":36800065},{"seriesIdentifiers":[36846763,36846764,36846765],"seriesAndModality":[],"studyIdentifier":36804038}]},{"subjectId":"103190","project":"NLST","id":12193840,"modalities":["CT"],"bodyParts":["CHEST"],"species":["337915000"],"timepoints":{},"totalNumberOfStudies":2,"totalNumberOfSeries":5,"studyIdentifiers":[{"seriesIdentifiers":[12275098,12275099,12275100],"seriesAndModality":[],"studyIdentifier":12229622},{"seriesIdentifiers":[22593671,22593672],"seriesAndModality":[],"studyIdentifier":22551097}]},{"subjectId":"103192","project":"NLST","id":22514495,"modalities":["CT"],"bodyParts":["CHEST"],"species":["337915000"],"timepoints":{},"totalNumberOfStudies":3,"totalNumberOfSeries":9,"studyIdentifiers":[{"seriesIdentifiers":[22593283,22593284,22593285],"seriesAndModality":[],"studyIdentifier":22550949},{"seriesIdentifiers":[22607142,22607143,22607144],"seriesAndModality":[],"studyIdentifier":22555647},{"seriesIdentifiers":[22607288,22607289,22607290],"seriesAndModality":[],"studyIdentifier":22555695}]},{"subjectId":"103195","project":"NLST","id":12191342,"modalities":["CT"],"bodyParts":["CHEST"],"species":["337915000"],"timepoints":{},"totalNumberOfStudies":3,"totalNumberOfSeries":9,"studyIdentifiers":[{"seriesIdentifiers":[12262217,12262218,12262219],"seriesAndModality":[],"studyIdentifier":12224921},{"seriesIdentifiers":[12262226,12262227,12262228],"seriesAndModality":[],"studyIdentifier":12224924},{"seriesIdentifiers":[21105863,21105864,21105865],"seriesAndModality":[],"studyIdentifier":12234859}]},{"subjectId":"103198","project":"NLST","id":32768028,"modalities":["CT"],"bodyParts":["CHEST"],"species":["337915000"],"timepoints":{},"totalNumberOfStudies":3,"totalNumberOfSeries":9,"studyIdentifiers":[{"seriesIdentifiers":[32737729,32737730,32737731],"seriesAndModality":[],"studyIdentifier":32702940},{"seriesIdentifiers":[32738156,32738157,32738158],"seriesAndModality":[],"studyIdentifier":32703084},{"seriesIdentifiers":[35849390,35849391,35849392],"seriesAndModality":[],"studyIdentifier":35815825}]},{"subjectId":"103199","project":"NLST","id":22512477,"modalities":["CT"],"bodyParts":["CHEST"],"species":["337915000"],"timepoints":{},"totalNumberOfStudies":3,"totalNumberOfSeries":6,"studyIdentifiers":[{"seriesIdentifiers":[22581245,22581246],"seriesAndModality":[],"studyIdentifier":22546218},{"seriesIdentifiers":[22581265,22581266],"seriesAndModality":[],"studyIdentifier":22546228},{"seriesIdentifiers":[22581998,22581999],"seriesAndModality":[],"studyIdentifier":22546582}]},{"subjectId":"103200","project":"NLST","id":12192218,"modalities":["CT"],"bodyParts":["CHEST"],"species":["337915000"],"timepoints":{},"totalNumberOfStudies":3,"totalNumberOfSeries":6,"studyIdentifiers":[{"seriesIdentifiers":[12266391,12266392],"seriesAndModality":[],"studyIdentifier":12226497},{"seriesIdentifiers":[36836961,36836962],"seriesAndModality":[],"studyIdentifier":36800404},{"seriesIdentifiers":[36837155,36837156],"seriesAndModality":[],"studyIdentifier":36800481}]},{"subjectId":"103206","project":"NLST","id":12193564,"modalities":["CT"],"bodyParts":["CHEST"],"species":["337915000"],"timepoints":{},"totalNumberOfStudies":3,"totalNumberOfSeries":16,"studyIdentifiers":[{"seriesIdentifiers":[12273580,12273581,12273582,12273583,12273584,12273585],"seriesAndModality":[],"studyIdentifier":12229106},{"seriesIdentifiers":[12286316,12286317,12286318,12286319,12286320],"seriesAndModality":[],"studyIdentifier":12233262},{"seriesIdentifiers":[32736370,32736371,32736372,32736373,32736374],"seriesAndModality":[],"studyIdentifier":32702699}]},{"subjectId":"103208","project":"NLST","id":12194742,"modalities":["CT"],"bodyParts":["CHEST"],"species":["337915000"],"timepoints":{},"totalNumberOfStudies":3,"totalNumberOfSeries":5,"studyIdentifiers":[{"seriesIdentifiers":[12281390,12281391],"seriesAndModality":[],"studyIdentifier":12231640},{"seriesIdentifiers":[22579161],"seriesAndModality":[],"studyIdentifier":22545189},{"seriesIdentifiers":[22593437,22593438],"seriesAndModality":[],"studyIdentifier":22551005}]},{"subjectId":"103210","project":"NLST","id":22513281,"modalities":["CT"],"bodyParts":["CHEST"],"species":["337915000"],"timepoints":{},"totalNumberOfStudies":3,"totalNumberOfSeries":9,"studyIdentifiers":[{"seriesIdentifiers":[22585038,22585039,22585040],"seriesAndModality":[],"studyIdentifier":22547745},{"seriesIdentifiers":[22588478,22588479,22588480],"seriesAndModality":[],"studyIdentifier":22549091},{"seriesIdentifiers":[22589054,22589055,22589056],"seriesAndModality":[],"studyIdentifier":22549288}]},{"subjectId":"103211","project":"NLST","id":22511828,"modalities":["CT"],"bodyParts":["CHEST"],"species":["337915000"],"timepoints":{},"totalNumberOfStudies":3,"totalNumberOfSeries":8,"studyIdentifiers":[{"seriesIdentifiers":[22577821,22577822],"seriesAndModality":[],"studyIdentifier":22544656},{"seriesIdentifiers":[22604366,22604367,22604368],"seriesAndModality":[],"studyIdentifier":22554733},{"seriesIdentifiers":[22605291,22605292,22605293],"seriesAndModality":[],"studyIdentifier":22555126}]},{"subjectId":"103213","project":"NLST","id":12191609,"modalities":["CT"],"bodyParts":["CHEST"],"species":["337915000"],"timepoints":{},"totalNumberOfStudies":3,"totalNumberOfSeries":7,"studyIdentifiers":[{"seriesIdentifiers":[12263926,12263927],"seriesAndModality":[],"studyIdentifier":12225388},{"seriesIdentifiers":[32473125,32473126],"seriesAndModality":[],"studyIdentifier":32440338},{"seriesIdentifiers":[35848567,35848568,35848569],"seriesAndModality":[],"studyIdentifier":35815603}]},{"subjectId":"103214","project":"NLST","id":12189734,"modalities":["CT"],"bodyParts":["CHEST"],"species":["337915000"],"timepoints":{},"totalNumberOfStudies":3,"totalNumberOfSeries":9,"studyIdentifiers":[{"seriesIdentifiers":[12255356,12255357,12255358],"seriesAndModality":[],"studyIdentifier":12222506},{"seriesIdentifiers":[36840457,36840458,36840459],"seriesAndModality":[],"studyIdentifier":36801464},{"seriesIdentifiers":[36841774,36841775,36841776],"seriesAndModality":[],"studyIdentifier":36801964}]},{"subjectId":"103216","project":"NLST","id":35881037,"modalities":["CT"],"bodyParts":["CHEST"],"species":["337915000"],"timepoints":{},"totalNumberOfStudies":3,"totalNumberOfSeries":9,"studyIdentifiers":[{"seriesIdentifiers":[35850542,35850543,35850544],"seriesAndModality":[],"studyIdentifier":35816248},{"seriesIdentifiers":[35850545,35850546,35850547],"seriesAndModality":[],"studyIdentifier":35816249},{"seriesIdentifiers":[35850895,35850896,35850897],"seriesAndModality":[],"studyIdentifier":35816366}]},{"subjectId":"103217","project":"NLST","id":6358757,"modalities":["CT"],"bodyParts":["CHEST"],"species":["337915000"],"timepoints":{},"totalNumberOfStudies":3,"totalNumberOfSeries":9,"studyIdentifiers":[{"seriesIdentifiers":[6432984,6432985,6432986],"seriesAndModality":[],"studyIdentifier":6393254},{"seriesIdentifiers":[9737805,9737806,9737807],"seriesAndModality":[],"studyIdentifier":9767368},{"seriesIdentifiers":[12283185,12283186,12283187],"seriesAndModality":[],"studyIdentifier":12232283}]},{"subjectId":"103218","project":"NLST","id":12193051,"modalities":["CT"],"bodyParts":["CHEST"],"species":["337915000"],"timepoints":{},"totalNumberOfStudies":3,"totalNumberOfSeries":7,"studyIdentifiers":[{"seriesIdentifiers":[12270960,12270961],"seriesAndModality":[],"studyIdentifier":12228151},{"seriesIdentifiers":[12276684,12276685],"seriesAndModality":[],"studyIdentifier":12229965},{"seriesIdentifiers":[32473141,32473142,32473143],"seriesAndModality":[],"studyIdentifier":32440346}]},{"subjectId":"103220","project":"NLST","id":12195912,"modalities":["CT"],"bodyParts":["CHEST"],"species":["337915000"],"timepoints":{},"totalNumberOfStudies":3,"totalNumberOfSeries":8,"studyIdentifiers":[{"seriesIdentifiers":[21104615,21104616],"seriesAndModality":[],"studyIdentifier":12234422},{"seriesIdentifiers":[21104638,21104639,21104640],"seriesAndModality":[],"studyIdentifier":12234431},{"seriesIdentifiers":[41910963,41910964,41910965],"seriesAndModality":[],"studyIdentifier":41877779}]},{"subjectId":"103222","project":"NLST","id":22515216,"modalities":["CT"],"bodyParts":["CHEST"],"species":["337915000"],"timepoints":{},"totalNumberOfStudies":3,"totalNumberOfSeries":6,"studyIdentifiers":[{"seriesIdentifiers":[22599811,22599812],"seriesAndModality":[],"studyIdentifier":22553306},{"seriesIdentifiers":[22599827,22599828],"seriesAndModality":[],"studyIdentifier":22553314},{"seriesIdentifiers":[30998652,30998653],"seriesAndModality":[],"studyIdentifier":22556835}]},{"subjectId":"103223","project":"NLST","id":12193654,"modalities":["CT"],"bodyParts":["CHEST"],"species":["337915000"],"timepoints":{},"totalNumberOfStudies":3,"totalNumberOfSeries":8,"studyIdentifiers":[{"seriesIdentifiers":[12274085,12274086,12274087],"seriesAndModality":[],"studyIdentifier":12229302},{"seriesIdentifiers":[41910528,41910529,41910530],"seriesAndModality":[],"studyIdentifier":41877624},{"seriesIdentifiers":[41910587,41910588],"seriesAndModality":[],"studyIdentifier":41877645}]},{"subjectId":"103225","project":"NLST","id":22514730,"modalities":["CT"],"bodyParts":["CHEST"],"species":["337915000"],"timepoints":{},"totalNumberOfStudies":3,"totalNumberOfSeries":17,"studyIdentifiers":[{"seriesIdentifiers":[22595107,22595108,22595109,22595110,22595111,22595112],"seriesAndModality":[],"studyIdentifier":22551519},{"seriesIdentifiers":[22601707,22601708,22601709,22601710,22601711],"seriesAndModality":[],"studyIdentifier":22553928},{"seriesIdentifiers":[32742108,32742109,32742110,32742111,32742112,32742113],"seriesAndModality":[],"studyIdentifier":32704181}]},{"subjectId":"103228","project":"NLST","id":9798624,"modalities":["CT"],"bodyParts":["CHEST"],"species":["337915000"],"timepoints":{},"totalNumberOfStudies":3,"totalNumberOfSeries":8,"studyIdentifiers":[{"seriesIdentifiers":[9737916,9737917],"seriesAndModality":[],"studyIdentifier":9767418},{"seriesIdentifiers":[32738859,32738860,32738861],"seriesAndModality":[],"studyIdentifier":32703298},{"seriesIdentifiers":[35849996,35849997,35849998],"seriesAndModality":[],"studyIdentifier":35816032}]},{"subjectId":"103229","project":"NLST","id":6357933,"modalities":["CT"],"bodyParts":["CHEST"],"species":["337915000"],"timepoints":{},"totalNumberOfStudies":3,"totalNumberOfSeries":6,"studyIdentifiers":[{"seriesIdentifiers":[6427599,6427600],"seriesAndModality":[],"studyIdentifier":6391534},{"seriesIdentifiers":[6427762,6427763],"seriesAndModality":[],"studyIdentifier":6391615},{"seriesIdentifiers":[12266467,12266468],"seriesAndModality":[],"studyIdentifier":12226535}]},{"subjectId":"103230","project":"NLST","id":36962941,"modalities":["CT"],"bodyParts":["CHEST"],"species":["337915000"],"timepoints":{},"totalNumberOfStudies":3,"totalNumberOfSeries":6,"studyIdentifiers":[{"seriesIdentifiers":[36843908,36843909],"seriesAndModality":[],"studyIdentifier":36802843},{"seriesIdentifiers":[36844087,36844088],"seriesAndModality":[],"studyIdentifier":36802932},{"seriesIdentifiers":[36844173,36844174],"seriesAndModality":[],"studyIdentifier":36802975}]},{"subjectId":"103232","project":"NLST","id":9798487,"modalities":["CT"],"bodyParts":["CHEST"],"species":["337915000"],"timepoints":{},"totalNumberOfStudies":1,"totalNumberOfSeries":2,"studyIdentifiers":[{"seriesIdentifiers":[9737170,9737171],"seriesAndModality":[],"studyIdentifier":9767066}]},{"subjectId":"103234","project":"NLST","id":12193747,"modalities":["CT"],"bodyParts":["CHEST"],"species":["337915000"],"timepoints":{},"totalNumberOfStudies":3,"totalNumberOfSeries":9,"studyIdentifiers":[{"seriesIdentifiers":[12274380,12274381,12274382],"seriesAndModality":[],"studyIdentifier":12229400},{"seriesIdentifiers":[21107056,21107057,21107058],"seriesAndModality":[],"studyIdentifier":12235265},{"seriesIdentifiers":[22590908,22590909,22590910],"seriesAndModality":[],"studyIdentifier":22550113}]},{"subjectId":"103235","project":"NLST","id":12192386,"modalities":["CT"],"bodyParts":["CHEST"],"species":["337915000"],"timepoints":{},"totalNumberOfStudies":3,"totalNumberOfSeries":6,"studyIdentifiers":[{"seriesIdentifiers":[12267228,12267229],"seriesAndModality":[],"studyIdentifier":12226879},{"seriesIdentifiers":[12267354,12267355],"seriesAndModality":[],"studyIdentifier":12226940},{"seriesIdentifiers":[22605172,22605173],"seriesAndModality":[],"studyIdentifier":22555072}]},{"subjectId":"103236","project":"NLST","id":12195587,"modalities":["CT"],"bodyParts":["CHEST"],"species":["337915000"],"timepoints":{},"totalNumberOfStudies":3,"totalNumberOfSeries":6,"studyIdentifiers":[{"seriesIdentifiers":[12287293,12287294],"seriesAndModality":[],"studyIdentifier":12233618},{"seriesIdentifiers":[12287324,12287325],"seriesAndModality":[],"studyIdentifier":12233633},{"seriesIdentifiers":[22609225,22609226],"seriesAndModality":[],"studyIdentifier":22556524}]},{"subjectId":"103238","project":"NLST","id":22515945,"modalities":["CT"],"bodyParts":["CHEST"],"species":["337915000"],"timepoints":{},"totalNumberOfStudies":3,"totalNumberOfSeries":9,"studyIdentifiers":[{"seriesIdentifiers":[22609799,22609800,22609801],"seriesAndModality":[],"studyIdentifier":22556737},{"seriesIdentifiers":[35849639,35849640,35849641],"seriesAndModality":[],"studyIdentifier":35815915},{"seriesIdentifiers":[35849642,35849643,35849644],"seriesAndModality":[],"studyIdentifier":35815916}]},{"subjectId":"103240","project":"NLST","id":22514513,"modalities":["CT"],"bodyParts":["CHEST"],"species":["337915000"],"timepoints":{},"totalNumberOfStudies":3,"totalNumberOfSeries":8,"studyIdentifiers":[{"seriesIdentifiers":[22593356,22593357],"seriesAndModality":[],"studyIdentifier":22550974},{"seriesIdentifiers":[22607160,22607161,22607162],"seriesAndModality":[],"studyIdentifier":22555653},{"seriesIdentifiers":[22607645,22607646,22607647],"seriesAndModality":[],"studyIdentifier":22555828}]},{"subjectId":"103241","project":"NLST","id":3342723,"modalities":["CT"],"bodyParts":["CHEST"],"species":["337915000"],"timepoints":{},"totalNumberOfStudies":3,"totalNumberOfSeries":17,"studyIdentifiers":[{"seriesIdentifiers":[32741338,32741339,32741340,32741341,32741342,32741343],"seriesAndModality":[],"studyIdentifier":32704019}]},{"subjectId":"103242","project":"NLST","id":12192701,"modalities":["CT"],"bodyParts":["CHEST"],"species":["337915000"],"timepoints":{},"totalNumberOfStudies":3,"totalNumberOfSeries":10,"studyIdentifiers":[{"seriesIdentifiers":[12269007,12269008,12269009],"seriesAndModality":[],"studyIdentifier":12227495},{"seriesIdentifiers":[12279485,12279486,12279487,12279488],"seriesAndModality":[],"studyIdentifier":12230891},{"seriesIdentifiers":[36845108,36845109,36845110],"seriesAndModality":[],"studyIdentifier":36803403}]},{"subjectId":"103243","project":"NLST","id":22513185,"modalities":["CT"],"bodyParts":["CHEST"],"species":["337915000"],"timepoints":{},"totalNumberOfStudies":3,"totalNumberOfSeries":8,"studyIdentifiers":[{"seriesIdentifiers":[22584669,22584670,22584671],"seriesAndModality":[],"studyIdentifier":22547600},{"seriesIdentifiers":[22584910,22584911],"seriesAndModality":[],"studyIdentifier":22547694},{"seriesIdentifiers":[22588316,22588317,22588318],"seriesAndModality":[],"studyIdentifier":22549035}]},{"subjectId":"103248","project":"NLST","id":12194045,"modalities":["CT"],"bodyParts":["CHEST"],"species":["337915000"],"timepoints":{},"totalNumberOfStudies":3,"totalNumberOfSeries":18,"studyIdentifiers":[{"seriesIdentifiers":[12276889,12276890,12276891,12276892,12276893,12276894],"seriesAndModality":[],"studyIdentifier":12230045},{"seriesIdentifiers":[22606087,22606088,22606089,22606090,22606091,22606092],"seriesAndModality":[],"studyIdentifier":22555461},{"seriesIdentifiers":[32737510,32737511,32737512,32737513,32737514,32737515],"seriesAndModality":[],"studyIdentifier":32702902}]},{"subjectId":"103249","project":"NLST","id":12190576,"modalities":["CT"],"bodyParts":["CHEST"],"species":["337915000"],"timepoints":{},"totalNumberOfStudies":3,"totalNumberOfSeries":9,"studyIdentifiers":[{"seriesIdentifiers":[12258646,12258647,12258648],"seriesAndModality":[],"studyIdentifier":12223649},{"seriesIdentifiers":[12284213,12284214,12284215],"seriesAndModality":[],"studyIdentifier":12232623},{"seriesIdentifiers":[36838185,36838186,36838187],"seriesAndModality":[],"studyIdentifier":36800853}]},{"subjectId":"103250","project":"NLST","id":32768142,"modalities":["CT"],"bodyParts":["CHEST"],"species":["337915000"],"timepoints":{},"totalNumberOfStudies":3,"totalNumberOfSeries":6,"studyIdentifiers":[{"seriesIdentifiers":[32739360,32739361],"seriesAndModality":[],"studyIdentifier":32703490},{"seriesIdentifiers":[32742747,32742748],"seriesAndModality":[],"studyIdentifier":32704387},{"seriesIdentifiers":[32742775,32742776],"seriesAndModality":[],"studyIdentifier":32704401}]},{"subjectId":"103251","project":"NLST","id":36962505,"modalities":["CT"],"bodyParts":["CHEST"],"species":["337915000"],"timepoints":{},"totalNumberOfStudies":3,"totalNumberOfSeries":6,"studyIdentifiers":[{"seriesIdentifiers":[36835295,36835296],"seriesAndModality":[],"studyIdentifier":36799695},{"seriesIdentifiers":[36835297,36835298],"seriesAndModality":[],"studyIdentifier":36799696},{"seriesIdentifiers":[36844227,36844228],"seriesAndModality":[],"studyIdentifier":36803002}]},{"subjectId":"103259","project":"NLST","id":9798717,"modalities":["CT"],"bodyParts":["CHEST"],"species":["337915000"],"timepoints":{},"totalNumberOfStudies":3,"totalNumberOfSeries":17,"studyIdentifiers":[{"seriesIdentifiers":[9739103,9739104,9739105,9739106,9739107],"seriesAndModality":[],"studyIdentifier":9767862},{"seriesIdentifiers":[9739410,9739411,9739412,9739413,9739414,9739415],"seriesAndModality":[],"studyIdentifier":9767916},{"seriesIdentifiers":[36847515,36847516,36847517,36847518,36847519,36847520],"seriesAndModality":[],"studyIdentifier":36804264}]}],"totalPatients":25970,"bodyParts":[{"value":"CHEST","count":25970}],"modalities":[{"value":"CT","count":25970}],"collections":[{"value":"NLST","count":25970}],"species":[{"value":"337915000","count":25970}],"maxTimepoints":{},"minTimepoints":{},"sort":"subject-ascending"}