{"resultSet":[{"subjectId":"217634","project":"NLST","id":54067237,"modalities":["CT"],"bodyParts":["CHEST"],"species":["337915000"],"timepoints":{},"totalNumberOfStudies":3,"totalNumberOfSeries":5,"studyIdentifiers":[{"seriesIdentifiers":[54165549,54169016],"seriesAndModality":[],"studyIdentifier":54100006},{"seriesIdentifiers":[63638081,63638082],"seriesAndModality":[],"studyIdentifier":63668884},{"seriesIdentifiers":[63638276],"seriesAndModality":[],"studyIdentifier":63668972}]},{"subjectId":"217638","project":"NLST","id":66290253,"modalities":["CT"],"bodyParts":["CHEST"],"species":["337915000"],"timepoints":{},"totalNumberOfStudies":3,"totalNumberOfSeries":6,"studyIdentifiers":[{"seriesIdentifiers":[66357399,75957241],"seriesAndModality":[],"studyIdentifier":66323297},{"seriesIdentifiers":[66359090,69730546],"seriesAndModality":[],"studyIdentifier":66324302},{"seriesIdentifiers":[66360099,66360101],"seriesAndModality":[],"studyIdentifier":66324870}]},{"subjectId":"217639","project":"NLST","id":66290907,"modalities":["CT"],"bodyParts":["CHEST"],"species":["337915000"],"timepoints":{},"totalNumberOfStudies":3,"totalNumberOfSeries":6,"studyIdentifiers":[{"seriesIdentifiers":[66360021,69730549],"seriesAndModality":[],"studyIdentifier":66324820},{"seriesIdentifiers":[69730547,69730548],"seriesAndModality":[],"studyIdentifier":69763120},{"seriesIdentifiers":[75956626,75956627],"seriesAndModality":[],"studyIdentifier":76087373}]},{"subjectId":"217640","project":"NLST","id":45810387,"modalities":["CT"],"bodyParts":["CHEST"],"species":["337915000"],"timepoints":{},"totalNumberOfStudies":3,"totalNumberOfSeries":8,"studyIdentifiers":[{"seriesIdentifiers":[45780133,45780150],"seriesAndModality":[],"studyIdentifier":45843856},{"seriesIdentifiers":[45781402,45781433,45781434],"seriesAndModality":[],"studyIdentifier":45844334},{"seriesIdentifiers":[45781699,45781896,45781897],"seriesAndModality":[],"studyIdentifier":45844522}]},{"subjectId":"217644","project":"NLST","id":54069418,"modalities":["CT"],"bodyParts":["CHEST"],"species":["337915000"],"timepoints":{},"totalNumberOfStudies":3,"totalNumberOfSeries":9,"studyIdentifiers":[{"seriesIdentifiers":[54174874,54174875,54174876],"seriesAndModality":[],"studyIdentifier":54104904},{"seriesIdentifiers":[54176000,54176001,54176002],"seriesAndModality":[],"studyIdentifier":54105350},{"seriesIdentifiers":[54177837,54177838,54177839],"seriesAndModality":[],"studyIdentifier":54106025}]},{"subjectId":"217647","project":"NLST","id":72516248,"modalities":["CT"],"bodyParts":["CHEST"],"species":["337915000"],"timepoints":{},"totalNumberOfStudies":1,"totalNumberOfSeries":2,"studyIdentifiers":[{"seriesIdentifiers":[72390660,72390661],"seriesAndModality":[],"studyIdentifier":72353929}]},{"subjectId":"217648","project":"NLST","id":54068853,"modalities":["CT"],"bodyParts":["CHEST"],"species":["337915000"],"timepoints":{},"totalNumberOfStudies":3,"totalNumberOfSeries":3,"studyIdentifiers":[{"seriesIdentifiers":[54170747],"seriesAndModality":[],"studyIdentifier":54102812},{"seriesIdentifiers":[54170932],"seriesAndModality":[],"studyIdentifier":54102964},{"seriesIdentifiers":[54171780],"seriesAndModality":[],"studyIdentifier":54103582}]},{"subjectId":"217649","project":"NLST","id":45810806,"modalities":["CT"],"bodyParts":["CHEST"],"species":["337915000"],"timepoints":{},"totalNumberOfStudies":2,"totalNumberOfSeries":4,"studyIdentifiers":[{"seriesIdentifiers":[45783215,45783216],"seriesAndModality":[],"studyIdentifier":45844936},{"seriesIdentifiers":[52560363,52560364],"seriesAndModality":[],"studyIdentifier":52527330}]},{"subjectId":"217651","project":"NLST","id":52494630,"modalities":["CT"],"bodyParts":["CHEST"],"species":["337915000"],"timepoints":{},"totalNumberOfStudies":1,"totalNumberOfSeries":2,"studyIdentifiers":[{"seriesIdentifiers":[52560644,52560645],"seriesAndModality":[],"studyIdentifier":52527466}]},{"subjectId":"217655","project":"NLST","id":54070341,"modalities":["CT"],"bodyParts":["CHEST"],"species":["337915000"],"timepoints":{},"totalNumberOfStudies":3,"totalNumberOfSeries":6,"studyIdentifiers":[{"seriesIdentifiers":[54183004,54183005],"seriesAndModality":[],"studyIdentifier":54107952},{"seriesIdentifiers":[54184001,54184002],"seriesAndModality":[],"studyIdentifier":54108457},{"seriesIdentifiers":[54184626,54184627],"seriesAndModality":[],"studyIdentifier":54108784}]},{"subjectId":"217657","project":"NLST","id":45810410,"modalities":["CT"],"bodyParts":["CHEST"],"species":["337915000"],"timepoints":{},"totalNumberOfStudies":3,"totalNumberOfSeries":8,"studyIdentifiers":[{"seriesIdentifiers":[45780190,45780191],"seriesAndModality":[],"studyIdentifier":45843881},{"seriesIdentifiers":[45781404,45781437,45781438],"seriesAndModality":[],"studyIdentifier":45844336},{"seriesIdentifiers":[45781718,45781937,45781938],"seriesAndModality":[],"studyIdentifier":45844541}]},{"subjectId":"217658","project":"NLST","id":66290767,"modalities":["CT"],"bodyParts":["CHEST"],"species":["337915000"],"timepoints":{},"totalNumberOfStudies":1,"totalNumberOfSeries":2,"studyIdentifiers":[{"seriesIdentifiers":[66359026,66359027],"seriesAndModality":[],"studyIdentifier":66324268}]},{"subjectId":"217659","project":"NLST","id":72516294,"modalities":["CT"],"bodyParts":["CHEST"],"species":["337915000"],"timepoints":{},"totalNumberOfStudies":3,"totalNumberOfSeries":6,"studyIdentifiers":[{"seriesIdentifiers":[72391965,72392060],"seriesAndModality":[],"studyIdentifier":72354561},{"seriesIdentifiers":[72392818,72392845],"seriesAndModality":[],"studyIdentifier":72354887},{"seriesIdentifiers":[75956865,75956866],"seriesAndModality":[],"studyIdentifier":76087412}]},{"subjectId":"217662","project":"NLST","id":54070519,"modalities":["CT"],"bodyParts":["CHEST"],"species":["337915000"],"timepoints":{},"totalNumberOfStudies":3,"totalNumberOfSeries":7,"studyIdentifiers":[{"seriesIdentifiers":[54183487,54183488],"seriesAndModality":[],"studyIdentifier":54108182},{"seriesIdentifiers":[54184254,54184255],"seriesAndModality":[],"studyIdentifier":54108591},{"seriesIdentifiers":[62259393,62259394,62259395],"seriesAndModality":[],"studyIdentifier":62226505}]},{"subjectId":"217666","project":"NLST","id":54069194,"modalities":["CT"],"bodyParts":["CHEST"],"species":["337915000"],"timepoints":{},"totalNumberOfStudies":3,"totalNumberOfSeries":9,"studyIdentifiers":[{"seriesIdentifiers":[54174258,54174259,75957080],"seriesAndModality":[],"studyIdentifier":54104646},{"seriesIdentifiers":[54175399,54175400,75956847],"seriesAndModality":[],"studyIdentifier":54105113},{"seriesIdentifiers":[54177735,54177736,54177737],"seriesAndModality":[],"studyIdentifier":54105989}]},{"subjectId":"217669","project":"NLST","id":72515667,"modalities":["CT"],"bodyParts":["CHEST"],"species":["337915000"],"timepoints":{},"totalNumberOfStudies":2,"totalNumberOfSeries":7,"studyIdentifiers":[{"seriesIdentifiers":[72385383,72385384,72385385,72385386],"seriesAndModality":[],"studyIdentifier":72352015},{"seriesIdentifiers":[72388263,72388264,72388265],"seriesAndModality":[],"studyIdentifier":72352850}]},{"subjectId":"217673","project":"NLST","id":54068031,"modalities":["CT"],"bodyParts":["CHEST"],"species":["337915000"],"timepoints":{},"totalNumberOfStudies":3,"totalNumberOfSeries":6,"studyIdentifiers":[{"seriesIdentifiers":[54166878,54169221],"seriesAndModality":[],"studyIdentifier":54101005},{"seriesIdentifiers":[54169250],"seriesAndModality":[],"studyIdentifier":54102132},{"seriesIdentifiers":[54169755,54169756,62261292],"seriesAndModality":[],"studyIdentifier":54102318}]},{"subjectId":"217675","project":"NLST","id":45809852,"modalities":["CT"],"bodyParts":["CHEST"],"species":["337915000"],"timepoints":{},"totalNumberOfStudies":3,"totalNumberOfSeries":6,"studyIdentifiers":[{"seriesIdentifiers":[45778364,45778818],"seriesAndModality":[],"studyIdentifier":45842976},{"seriesIdentifiers":[45778860,45778861],"seriesAndModality":[],"studyIdentifier":45843218},{"seriesIdentifiers":[72391103,72391491],"seriesAndModality":[],"studyIdentifier":72354174}]},{"subjectId":"217676","project":"NLST","id":54068919,"modalities":["CT"],"bodyParts":["CHEST"],"species":["337915000"],"timepoints":{},"totalNumberOfStudies":3,"totalNumberOfSeries":4,"studyIdentifiers":[{"seriesIdentifiers":[54170889],"seriesAndModality":[],"studyIdentifier":54102926},{"seriesIdentifiers":[54171894,54171895],"seriesAndModality":[],"studyIdentifier":54103666},{"seriesIdentifiers":[54171904],"seriesAndModality":[],"studyIdentifier":54103673}]},{"subjectId":"217679","project":"NLST","id":54070314,"modalities":["CT"],"bodyParts":["CHEST"],"species":["337915000"],"timepoints":{},"totalNumberOfStudies":3,"totalNumberOfSeries":6,"studyIdentifiers":[{"seriesIdentifiers":[54182949,54182950],"seriesAndModality":[],"studyIdentifier":54107924},{"seriesIdentifiers":[54183953,54183954],"seriesAndModality":[],"studyIdentifier":54108432},{"seriesIdentifiers":[54185133,63636475],"seriesAndModality":[],"studyIdentifier":54109001}]},{"subjectId":"217680","project":"NLST","id":72516300,"modalities":["CT"],"bodyParts":["CHEST"],"species":["337915000"],"timepoints":{},"totalNumberOfStudies":3,"totalNumberOfSeries":7,"studyIdentifiers":[{"seriesIdentifiers":[72391984,72392004],"seriesAndModality":[],"studyIdentifier":72354570},{"seriesIdentifiers":[72392145,72392146,72392164],"seriesAndModality":[],"studyIdentifier":72354634},{"seriesIdentifiers":[72392397,72392398],"seriesAndModality":[],"studyIdentifier":72354728}]},{"subjectId":"217685","project":"NLST","id":54070461,"modalities":["CT"],"bodyParts":["CHEST"],"species":["337915000"],"timepoints":{},"totalNumberOfStudies":3,"totalNumberOfSeries":7,"studyIdentifiers":[{"seriesIdentifiers":[54183332,54183333],"seriesAndModality":[],"studyIdentifier":54108097},{"seriesIdentifiers":[54184149,54184150],"seriesAndModality":[],"studyIdentifier":54108539},{"seriesIdentifiers":[54184992,54184993,54184994],"seriesAndModality":[],"studyIdentifier":54108945}]},{"subjectId":"217688","project":"NLST","id":54068975,"modalities":["CT"],"bodyParts":["CHEST"],"species":["337915000"],"timepoints":{},"totalNumberOfStudies":3,"totalNumberOfSeries":3,"studyIdentifiers":[{"seriesIdentifiers":[54171052],"seriesAndModality":[],"studyIdentifier":54103063},{"seriesIdentifiers":[54171306],"seriesAndModality":[],"studyIdentifier":54103260},{"seriesIdentifiers":[62261865],"seriesAndModality":[],"studyIdentifier":62227362}]},{"subjectId":"217689","project":"NLST","id":45809867,"modalities":["CT"],"bodyParts":["CHEST"],"species":["337915000"],"timepoints":{},"totalNumberOfStudies":3,"totalNumberOfSeries":6,"studyIdentifiers":[{"seriesIdentifiers":[45778379,45778839],"seriesAndModality":[],"studyIdentifier":45842991},{"seriesIdentifiers":[45780039,45780041],"seriesAndModality":[],"studyIdentifier":45843806},{"seriesIdentifiers":[72391114,72391131],"seriesAndModality":[],"studyIdentifier":72354181}]},{"subjectId":"217690","project":"NLST","id":45810914,"modalities":["CT"],"bodyParts":["CHEST"],"species":["337915000"],"timepoints":{},"totalNumberOfStudies":3,"totalNumberOfSeries":12,"studyIdentifiers":[{"seriesIdentifiers":[45783607,45783610,45783611,45783612],"seriesAndModality":[],"studyIdentifier":45845075},{"seriesIdentifiers":[48726605,48726606,48726607,48726608],"seriesAndModality":[],"studyIdentifier":48791696},{"seriesIdentifiers":[48727880,48727882,48727883,48727884],"seriesAndModality":[],"studyIdentifier":48792094}]},{"subjectId":"217693","project":"NLST","id":72516065,"modalities":["CT"],"bodyParts":["CHEST"],"species":["337915000"],"timepoints":{},"totalNumberOfStudies":3,"totalNumberOfSeries":5,"studyIdentifiers":[{"seriesIdentifiers":[72389211],"seriesAndModality":[],"studyIdentifier":72353191},{"seriesIdentifiers":[72389294,72389295],"seriesAndModality":[],"studyIdentifier":72353237},{"seriesIdentifiers":[72389643,72389644],"seriesAndModality":[],"studyIdentifier":72353421}]},{"subjectId":"217700","project":"NLST","id":66289750,"modalities":["CT"],"bodyParts":["CHEST"],"species":["337915000"],"timepoints":{},"totalNumberOfStudies":3,"totalNumberOfSeries":6,"studyIdentifiers":[{"seriesIdentifiers":[66355398,69730554],"seriesAndModality":[],"studyIdentifier":66322548},{"seriesIdentifiers":[66360875,69730558],"seriesAndModality":[],"studyIdentifier":66325186},{"seriesIdentifiers":[69730552,69730553],"seriesAndModality":[],"studyIdentifier":69763122}]},{"subjectId":"217701","project":"NLST","id":66289869,"modalities":["CT"],"bodyParts":["CHEST"],"species":["337915000"],"timepoints":{},"totalNumberOfStudies":3,"totalNumberOfSeries":12,"studyIdentifiers":[{"seriesIdentifiers":[66355731,66355732,69730566,69730567],"seriesAndModality":[],"studyIdentifier":66322703},{"seriesIdentifiers":[66357009,69730559,69730560,69730561],"seriesAndModality":[],"studyIdentifier":66323157},{"seriesIdentifiers":[69730562,69730563,69730564,69730565],"seriesAndModality":[],"studyIdentifier":69763124}]},{"subjectId":"217702","project":"NLST","id":50135769,"modalities":["CT"],"bodyParts":["CHEST"],"species":["337915000"],"timepoints":{},"totalNumberOfStudies":3,"totalNumberOfSeries":10,"studyIdentifiers":[{"seriesIdentifiers":[50202650,50202651,50202739],"seriesAndModality":[],"studyIdentifier":50168770},{"seriesIdentifiers":[50202719,50202741,50202745],"seriesAndModality":[],"studyIdentifier":50168784},{"seriesIdentifiers":[62259866,62259867,62259868,62259869],"seriesAndModality":[],"studyIdentifier":62226673}]},{"subjectId":"217706","project":"NLST","id":66290462,"modalities":["CT"],"bodyParts":["CHEST"],"species":["337915000"],"timepoints":{},"totalNumberOfStudies":1,"totalNumberOfSeries":2,"studyIdentifiers":[{"seriesIdentifiers":[66357808,66357810],"seriesAndModality":[],"studyIdentifier":66323561}]},{"subjectId":"217709","project":"NLST","id":66289751,"modalities":["CT"],"bodyParts":["CHEST"],"species":["337915000"],"timepoints":{},"totalNumberOfStudies":3,"totalNumberOfSeries":6,"studyIdentifiers":[{"seriesIdentifiers":[66355399,66360404],"seriesAndModality":[],"studyIdentifier":66322549},{"seriesIdentifiers":[66358597,66360922],"seriesAndModality":[],"studyIdentifier":66324001},{"seriesIdentifiers":[69730568,75957390],"seriesAndModality":[],"studyIdentifier":69763125}]},{"subjectId":"217710","project":"NLST","id":54067776,"modalities":["CT"],"bodyParts":["CHEST"],"species":["337915000"],"timepoints":{},"totalNumberOfStudies":3,"totalNumberOfSeries":3,"studyIdentifiers":[{"seriesIdentifiers":[54166363],"seriesAndModality":[],"studyIdentifier":54100624},{"seriesIdentifiers":[54167808],"seriesAndModality":[],"studyIdentifier":54101519},{"seriesIdentifiers":[54169940],"seriesAndModality":[],"studyIdentifier":54102369}]},{"subjectId":"217712","project":"NLST","id":45810315,"modalities":["CT"],"bodyParts":["CHEST"],"species":["337915000"],"timepoints":{},"totalNumberOfStudies":3,"totalNumberOfSeries":6,"studyIdentifiers":[{"seriesIdentifiers":[45779394,45779395],"seriesAndModality":[],"studyIdentifier":45843483},{"seriesIdentifiers":[45779843,45779857],"seriesAndModality":[],"studyIdentifier":45843708},{"seriesIdentifiers":[72391359,72391382],"seriesAndModality":[],"studyIdentifier":72354297}]},{"subjectId":"217713","project":"NLST","id":63995957,"modalities":["CT"],"bodyParts":["CHEST"],"species":["337915000"],"timepoints":{},"totalNumberOfStudies":3,"totalNumberOfSeries":7,"studyIdentifiers":[{"seriesIdentifiers":[63636973,63636974,63636975],"seriesAndModality":[],"studyIdentifier":63668368},{"seriesIdentifiers":[63637069,63637070,63637071],"seriesAndModality":[],"studyIdentifier":63668408},{"seriesIdentifiers":[63637082],"seriesAndModality":[],"studyIdentifier":63668414}]},{"subjectId":"217714","project":"NLST","id":45810706,"modalities":["CT"],"bodyParts":["CHEST"],"species":["337915000"],"timepoints":{},"totalNumberOfStudies":3,"totalNumberOfSeries":11,"studyIdentifiers":[{"seriesIdentifiers":[45781137,45781138,45781139],"seriesAndModality":[],"studyIdentifier":45844220},{"seriesIdentifiers":[45781418,45781449,45781450,45781526,45781527],"seriesAndModality":[],"studyIdentifier":45844350},{"seriesIdentifiers":[45781826,45781827,45781828],"seriesAndModality":[],"studyIdentifier":45844633}]},{"subjectId":"217720","project":"NLST","id":45810810,"modalities":["CT"],"bodyParts":["CHEST"],"species":["337915000"],"timepoints":{},"totalNumberOfStudies":2,"totalNumberOfSeries":4,"studyIdentifiers":[{"seriesIdentifiers":[45783223,45783224],"seriesAndModality":[],"studyIdentifier":45844940},{"seriesIdentifiers":[52560183,52560184],"seriesAndModality":[],"studyIdentifier":52527250}]},{"subjectId":"217723","project":"NLST","id":50135078,"modalities":["CT"],"bodyParts":["CHEST"],"species":["337915000"],"timepoints":{},"totalNumberOfStudies":2,"totalNumberOfSeries":5,"studyIdentifiers":[{"seriesIdentifiers":[50200627,50204280,50204313],"seriesAndModality":[],"studyIdentifier":50167847},{"seriesIdentifiers":[50205371,50205376],"seriesAndModality":[],"studyIdentifier":50169500}]},{"subjectId":"217724","project":"NLST","id":54067764,"modalities":["CT"],"bodyParts":["CHEST"],"species":["337915000"],"timepoints":{},"totalNumberOfStudies":3,"totalNumberOfSeries":6,"studyIdentifiers":[{"seriesIdentifiers":[54166345,54168251],"seriesAndModality":[],"studyIdentifier":54100610},{"seriesIdentifiers":[63638723,63638724],"seriesAndModality":[],"studyIdentifier":63669135},{"seriesIdentifiers":[63639010,63639011],"seriesAndModality":[],"studyIdentifier":63669233}]},{"subjectId":"217726","project":"NLST","id":54069573,"modalities":["CT"],"bodyParts":["CHEST"],"species":["337915000"],"timepoints":{},"totalNumberOfStudies":2,"totalNumberOfSeries":7,"studyIdentifiers":[{"seriesIdentifiers":[54175269,54175270,75956484],"seriesAndModality":[],"studyIdentifier":54105063},{"seriesIdentifiers":[54175902,54175903,54175904,63635643],"seriesAndModality":[],"studyIdentifier":54105311}]},{"subjectId":"217727","project":"NLST","id":72516402,"modalities":["CT"],"bodyParts":["CHEST"],"species":["337915000"],"timepoints":{},"totalNumberOfStudies":1,"totalNumberOfSeries":4,"studyIdentifiers":[{"seriesIdentifiers":[72392538,72392539,72392550,75956600],"seriesAndModality":[],"studyIdentifier":72354781}]},{"subjectId":"217728","project":"NLST","id":66289752,"modalities":["CT"],"bodyParts":["CHEST"],"species":["337915000"],"timepoints":{},"totalNumberOfStudies":3,"totalNumberOfSeries":6,"studyIdentifiers":[{"seriesIdentifiers":[66355400,66355401],"seriesAndModality":[],"studyIdentifier":66322550},{"seriesIdentifiers":[66355402,66358600],"seriesAndModality":[],"studyIdentifier":66322551},{"seriesIdentifiers":[69730571,69730572],"seriesAndModality":[],"studyIdentifier":69763126}]},{"subjectId":"217729","project":"NLST","id":50135459,"modalities":["CT"],"bodyParts":["CHEST"],"species":["337915000"],"timepoints":{},"totalNumberOfStudies":3,"totalNumberOfSeries":4,"studyIdentifiers":[{"seriesIdentifiers":[50201539],"seriesAndModality":[],"studyIdentifier":50168310},{"seriesIdentifiers":[50202890,50204329],"seriesAndModality":[],"studyIdentifier":50168849},{"seriesIdentifiers":[50205544],"seriesAndModality":[],"studyIdentifier":50169629}]},{"subjectId":"217730","project":"NLST","id":50135804,"modalities":["CT"],"bodyParts":["CHEST"],"species":["337915000"],"timepoints":{},"totalNumberOfStudies":3,"totalNumberOfSeries":10,"studyIdentifiers":[{"seriesIdentifiers":[50202903,50203549,50203550,50204626],"seriesAndModality":[],"studyIdentifier":50168857},{"seriesIdentifiers":[50203716,50204104,50204474],"seriesAndModality":[],"studyIdentifier":50169100},{"seriesIdentifiers":[50204639,50204651,50204663],"seriesAndModality":[],"studyIdentifier":50169281}]},{"subjectId":"217731","project":"NLST","id":45810773,"modalities":["CT"],"bodyParts":["CHEST"],"species":["337915000"],"timepoints":{},"totalNumberOfStudies":1,"totalNumberOfSeries":3,"studyIdentifiers":[{"seriesIdentifiers":[45781603,45782274,45782275],"seriesAndModality":[],"studyIdentifier":45844426}]},{"subjectId":"217740","project":"NLST","id":54067682,"modalities":["CT"],"bodyParts":["CHEST"],"species":["337915000"],"timepoints":{},"totalNumberOfStudies":3,"totalNumberOfSeries":6,"studyIdentifiers":[{"seriesIdentifiers":[54166191,54170278],"seriesAndModality":[],"studyIdentifier":54100510},{"seriesIdentifiers":[54167539,62261699],"seriesAndModality":[],"studyIdentifier":54101388},{"seriesIdentifiers":[54172289,54172290],"seriesAndModality":[],"studyIdentifier":54103905}]},{"subjectId":"217743","project":"NLST","id":50135061,"modalities":["CT"],"bodyParts":["CHEST"],"species":["337915000"],"timepoints":{},"totalNumberOfStudies":3,"totalNumberOfSeries":5,"studyIdentifiers":[{"seriesIdentifiers":[50200600,50204227,50204234],"seriesAndModality":[],"studyIdentifier":50167829},{"seriesIdentifiers":[50205233],"seriesAndModality":[],"studyIdentifier":50169422},{"seriesIdentifiers":[50205972],"seriesAndModality":[],"studyIdentifier":50169984}]},{"subjectId":"217744","project":"NLST","id":50135328,"modalities":["CT"],"bodyParts":["CHEST"],"species":["337915000"],"timepoints":{},"totalNumberOfStudies":3,"totalNumberOfSeries":12,"studyIdentifiers":[{"seriesIdentifiers":[50201198,50201212,50201215,50204775],"seriesAndModality":[],"studyIdentifier":50168141},{"seriesIdentifiers":[50202278,50202281,50202284,50202291],"seriesAndModality":[],"studyIdentifier":50168657},{"seriesIdentifiers":[50203165,50203827,50203840,50204465],"seriesAndModality":[],"studyIdentifier":50168960}]},{"subjectId":"217746","project":"NLST","id":54069124,"modalities":["CT"],"bodyParts":["CHEST"],"species":["337915000"],"timepoints":{},"totalNumberOfStudies":3,"totalNumberOfSeries":9,"studyIdentifiers":[{"seriesIdentifiers":[54174076,54174077,75956717],"seriesAndModality":[],"studyIdentifier":54104564},{"seriesIdentifiers":[54176058,54176059,63635656],"seriesAndModality":[],"studyIdentifier":54105372},{"seriesIdentifiers":[54177430,54177431,54177432],"seriesAndModality":[],"studyIdentifier":54105877}]},{"subjectId":"217749","project":"NLST","id":72516367,"modalities":["CT"],"bodyParts":["CHEST"],"species":["337915000"],"timepoints":{},"totalNumberOfStudies":1,"totalNumberOfSeries":3,"studyIdentifiers":[{"seriesIdentifiers":[72392268,72392269,72392305],"seriesAndModality":[],"studyIdentifier":72354679}]},{"subjectId":"217751","project":"NLST","id":54068521,"modalities":["CT"],"bodyParts":["CHEST"],"species":["337915000"],"timepoints":{},"totalNumberOfStudies":2,"totalNumberOfSeries":3,"studyIdentifiers":[{"seriesIdentifiers":[54168776,54168777],"seriesAndModality":[],"studyIdentifier":54101964},{"seriesIdentifiers":[54169770],"seriesAndModality":[],"studyIdentifier":54102324}]},{"subjectId":"217753","project":"NLST","id":66289753,"modalities":["CT"],"bodyParts":["CHEST"],"species":["337915000"],"timepoints":{},"totalNumberOfStudies":3,"totalNumberOfSeries":8,"studyIdentifiers":[{"seriesIdentifiers":[66355405,66355406,66359412,66359413],"seriesAndModality":[],"studyIdentifier":66322552},{"seriesIdentifiers":[66357983,66357985],"seriesAndModality":[],"studyIdentifier":66323659},{"seriesIdentifiers":[69730573,69730574],"seriesAndModality":[],"studyIdentifier":69763127}]},{"subjectId":"217755","project":"NLST","id":50135295,"modalities":["CT"],"bodyParts":["CHEST"],"species":["337915000"],"timepoints":{},"totalNumberOfStudies":3,"totalNumberOfSeries":10,"studyIdentifiers":[{"seriesIdentifiers":[50201124,50201140,50203972],"seriesAndModality":[],"studyIdentifier":50168102},{"seriesIdentifiers":[50201540,50204975,50204980],"seriesAndModality":[],"studyIdentifier":50168311},{"seriesIdentifiers":[62259952,62259953,62259954,62259955],"seriesAndModality":[],"studyIdentifier":62226697}]},{"subjectId":"217756","project":"NLST","id":63995922,"modalities":["CT"],"bodyParts":["CHEST"],"species":["337915000"],"timepoints":{},"totalNumberOfStudies":2,"totalNumberOfSeries":4,"studyIdentifiers":[{"seriesIdentifiers":[63636741,63636742,63636743],"seriesAndModality":[],"studyIdentifier":63668280},{"seriesIdentifiers":[63636936],"seriesAndModality":[],"studyIdentifier":63668356}]},{"subjectId":"217759","project":"NLST","id":54069429,"modalities":["CT"],"bodyParts":["CHEST"],"species":["337915000"],"timepoints":{},"totalNumberOfStudies":3,"totalNumberOfSeries":9,"studyIdentifiers":[{"seriesIdentifiers":[54174903,54174904,75957222],"seriesAndModality":[],"studyIdentifier":54104915},{"seriesIdentifiers":[54175789,54175790,75956356],"seriesAndModality":[],"studyIdentifier":54105268},{"seriesIdentifiers":[54178012,54178013,54178014],"seriesAndModality":[],"studyIdentifier":54106087}]},{"subjectId":"217762","project":"NLST","id":66290267,"modalities":["CT"],"bodyParts":["CHEST"],"species":["337915000"],"timepoints":{},"totalNumberOfStudies":3,"totalNumberOfSeries":6,"studyIdentifiers":[{"seriesIdentifiers":[66357419,75957297],"seriesAndModality":[],"studyIdentifier":66323315},{"seriesIdentifiers":[66358267,66358268],"seriesAndModality":[],"studyIdentifier":66323818},{"seriesIdentifiers":[75957058,75957059],"seriesAndModality":[],"studyIdentifier":76087461}]},{"subjectId":"217763","project":"NLST","id":52494409,"modalities":["CT"],"bodyParts":["CHEST"],"species":["337915000"],"timepoints":{},"totalNumberOfStudies":1,"totalNumberOfSeries":2,"studyIdentifiers":[{"seriesIdentifiers":[52560045,52560046],"seriesAndModality":[],"studyIdentifier":52527190}]},{"subjectId":"217764","project":"NLST","id":63996149,"modalities":["CT"],"bodyParts":["CHEST"],"species":["337915000"],"timepoints":{},"totalNumberOfStudies":2,"totalNumberOfSeries":4,"studyIdentifiers":[{"seriesIdentifiers":[63638161,63638162],"seriesAndModality":[],"studyIdentifier":63668919},{"seriesIdentifiers":[63638925,63638926],"seriesAndModality":[],"studyIdentifier":63669199}]},{"subjectId":"217767","project":"NLST","id":54068895,"modalities":["CT"],"bodyParts":["CHEST"],"species":["337915000"],"timepoints":{},"totalNumberOfStudies":3,"totalNumberOfSeries":4,"studyIdentifiers":[{"seriesIdentifiers":[54170853],"seriesAndModality":[],"studyIdentifier":54102895},{"seriesIdentifiers":[54171111],"seriesAndModality":[],"studyIdentifier":54103106},{"seriesIdentifiers":[54172037,54172038],"seriesAndModality":[],"studyIdentifier":54103745}]},{"subjectId":"217768","project":"NLST","id":72516237,"modalities":["CT"],"bodyParts":["CHEST"],"species":["337915000"],"timepoints":{},"totalNumberOfStudies":1,"totalNumberOfSeries":2,"studyIdentifiers":[{"seriesIdentifiers":[72390288,72390289],"seriesAndModality":[],"studyIdentifier":72353755}]},{"subjectId":"217769","project":"NLST","id":45810065,"modalities":["CT"],"bodyParts":["CHEST"],"species":["337915000"],"timepoints":{},"totalNumberOfStudies":3,"totalNumberOfSeries":6,"studyIdentifiers":[{"seriesIdentifiers":[45778577,45778797],"seriesAndModality":[],"studyIdentifier":45843189},{"seriesIdentifiers":[45779795,45779804],"seriesAndModality":[],"studyIdentifier":45843687},{"seriesIdentifiers":[72391073,72391106],"seriesAndModality":[],"studyIdentifier":72354161}]},{"subjectId":"217770","project":"NLST","id":45810430,"modalities":["CT"],"bodyParts":["CHEST"],"species":["337915000"],"timepoints":{},"totalNumberOfStudies":3,"totalNumberOfSeries":9,"studyIdentifiers":[{"seriesIdentifiers":[45780216,45780423,45780424],"seriesAndModality":[],"studyIdentifier":45843902},{"seriesIdentifiers":[45782422,45782423,45782424],"seriesAndModality":[],"studyIdentifier":45844660},{"seriesIdentifiers":[45782726,45783088,45783089],"seriesAndModality":[],"studyIdentifier":45844865}]},{"subjectId":"217771","project":"NLST","id":66290821,"modalities":["CT"],"bodyParts":["CHEST"],"species":["337915000"],"timepoints":{},"totalNumberOfStudies":3,"totalNumberOfSeries":6,"studyIdentifiers":[{"seriesIdentifiers":[66359328,66359329],"seriesAndModality":[],"studyIdentifier":66324426},{"seriesIdentifiers":[69730576,69730579],"seriesAndModality":[],"studyIdentifier":69763129},{"seriesIdentifiers":[75957498,75957499],"seriesAndModality":[],"studyIdentifier":76087516}]},{"subjectId":"217772","project":"NLST","id":54069774,"modalities":["CT"],"bodyParts":["CHEST"],"species":["337915000"],"timepoints":{},"totalNumberOfStudies":3,"totalNumberOfSeries":9,"studyIdentifiers":[{"seriesIdentifiers":[54178536,54178537,54178538],"seriesAndModality":[],"studyIdentifier":54106276},{"seriesIdentifiers":[54179843,54179844,63635997],"seriesAndModality":[],"studyIdentifier":54106765},{"seriesIdentifiers":[54180451,54180452,54180453],"seriesAndModality":[],"studyIdentifier":54106985}]},{"subjectId":"217773","project":"NLST","id":66289755,"modalities":["CT"],"bodyParts":["CHEST"],"species":["337915000"],"timepoints":{},"totalNumberOfStudies":3,"totalNumberOfSeries":6,"studyIdentifiers":[{"seriesIdentifiers":[66355408,69730581],"seriesAndModality":[],"studyIdentifier":66322554},{"seriesIdentifiers":[66355409,66358630],"seriesAndModality":[],"studyIdentifier":66322555},{"seriesIdentifiers":[66358848,66358849],"seriesAndModality":[],"studyIdentifier":66324143}]},{"subjectId":"217779","project":"NLST","id":62292106,"modalities":["CT"],"bodyParts":["CHEST"],"species":["337915000"],"timepoints":{},"totalNumberOfStudies":2,"totalNumberOfSeries":3,"studyIdentifiers":[{"seriesIdentifiers":[62261439,62261440],"seriesAndModality":[],"studyIdentifier":62227227},{"seriesIdentifiers":[63637717],"seriesAndModality":[],"studyIdentifier":63668719}]},{"subjectId":"217780","project":"NLST","id":54069206,"modalities":["CT"],"bodyParts":["CHEST"],"species":["337915000"],"timepoints":{},"totalNumberOfStudies":1,"totalNumberOfSeries":2,"studyIdentifiers":[{"seriesIdentifiers":[54174288,54174289],"seriesAndModality":[],"studyIdentifier":54104659}]},{"subjectId":"217781","project":"NLST","id":66290889,"modalities":["CT"],"bodyParts":["CHEST"],"species":["337915000"],"timepoints":{},"totalNumberOfStudies":3,"totalNumberOfSeries":6,"studyIdentifiers":[{"seriesIdentifiers":[66359702,69730588],"seriesAndModality":[],"studyIdentifier":66324641},{"seriesIdentifiers":[69730582,69730585],"seriesAndModality":[],"studyIdentifier":69763133},{"seriesIdentifiers":[69730586,69730587],"seriesAndModality":[],"studyIdentifier":69763135}]},{"subjectId":"217782","project":"NLST","id":66289831,"modalities":["CT"],"bodyParts":["CHEST"],"species":["337915000"],"timepoints":{},"totalNumberOfStudies":3,"totalNumberOfSeries":12,"studyIdentifiers":[{"seriesIdentifiers":[66355608,66355610,66355611,66355612],"seriesAndModality":[],"studyIdentifier":66322655},{"seriesIdentifiers":[66360771,66360772,69730589,69730590],"seriesAndModality":[],"studyIdentifier":66325165},{"seriesIdentifiers":[70517078,70517079,70517080,70517081],"seriesAndModality":[],"studyIdentifier":70582357}]},{"subjectId":"217784","project":"NLST","id":50135397,"modalities":["CT"],"bodyParts":["CHEST"],"species":["337915000"],"timepoints":{},"totalNumberOfStudies":3,"totalNumberOfSeries":10,"studyIdentifiers":[{"seriesIdentifiers":[50201400,50201652,50201679,50201717],"seriesAndModality":[],"studyIdentifier":50168226},{"seriesIdentifiers":[50203378,50204725,50204737,50204742],"seriesAndModality":[],"studyIdentifier":50169033},{"seriesIdentifiers":[50203979,50204839],"seriesAndModality":[],"studyIdentifier":50169185}]},{"subjectId":"217789","project":"NLST","id":54068205,"modalities":["CT"],"bodyParts":["CHEST"],"species":["337915000"],"timepoints":{},"totalNumberOfStudies":3,"totalNumberOfSeries":9,"studyIdentifiers":[{"seriesIdentifiers":[54167426,54168942,62261891],"seriesAndModality":[],"studyIdentifier":54101319},{"seriesIdentifiers":[54167693,54168532,62261952],"seriesAndModality":[],"studyIdentifier":54101464},{"seriesIdentifiers":[54172898,54172899,54172900],"seriesAndModality":[],"studyIdentifier":54104131}]},{"subjectId":"217791","project":"NLST","id":52494623,"modalities":["CT"],"bodyParts":["CHEST"],"species":["337915000"],"timepoints":{},"totalNumberOfStudies":1,"totalNumberOfSeries":2,"studyIdentifiers":[{"seriesIdentifiers":[52560630,52560631],"seriesAndModality":[],"studyIdentifier":52527459}]},{"subjectId":"217792","project":"NLST","id":54067445,"modalities":["CT"],"bodyParts":["CHEST"],"species":["337915000"],"timepoints":{},"totalNumberOfStudies":3,"totalNumberOfSeries":3,"studyIdentifiers":[{"seriesIdentifiers":[54165812],"seriesAndModality":[],"studyIdentifier":54100227},{"seriesIdentifiers":[54167313],"seriesAndModality":[],"studyIdentifier":54101274},{"seriesIdentifiers":[54167804],"seriesAndModality":[],"studyIdentifier":54101515}]},{"subjectId":"217793","project":"NLST","id":50135859,"modalities":["CT"],"bodyParts":["CHEST"],"species":["337915000"],"timepoints":{},"totalNumberOfStudies":3,"totalNumberOfSeries":7,"studyIdentifiers":[{"seriesIdentifiers":[50203451,50203466],"seriesAndModality":[],"studyIdentifier":50169043},{"seriesIdentifiers":[50205321,50205327,50205328,50205329],"seriesAndModality":[],"studyIdentifier":50169476},{"seriesIdentifiers":[50205982],"seriesAndModality":[],"studyIdentifier":50169993}]},{"subjectId":"217795","project":"NLST","id":54067813,"modalities":["CT"],"bodyParts":["CHEST"],"species":["337915000"],"timepoints":{},"totalNumberOfStudies":3,"totalNumberOfSeries":13,"studyIdentifiers":[{"seriesIdentifiers":[54166426,54166931,54167325,54169782,54169960,62261978],"seriesAndModality":[],"studyIdentifier":54100679},{"seriesIdentifiers":[54169634,54169635,54169636],"seriesAndModality":[],"studyIdentifier":54102268},{"seriesIdentifiers":[54173728,54173729,54173730,54173731],"seriesAndModality":[],"studyIdentifier":54104430}]},{"subjectId":"217797","project":"NLST","id":45810710,"modalities":["CT"],"bodyParts":["CHEST"],"species":["337915000"],"timepoints":{},"totalNumberOfStudies":3,"totalNumberOfSeries":8,"studyIdentifiers":[{"seriesIdentifiers":[45781148,45781149,45781150],"seriesAndModality":[],"studyIdentifier":45844224},{"seriesIdentifiers":[45781535,45781536],"seriesAndModality":[],"studyIdentifier":45844363},{"seriesIdentifiers":[45781681,45781857,45781858],"seriesAndModality":[],"studyIdentifier":45844504}]},{"subjectId":"217798","project":"NLST","id":54068959,"modalities":["CT"],"bodyParts":["CHEST"],"species":["337915000"],"timepoints":{},"totalNumberOfStudies":3,"totalNumberOfSeries":5,"studyIdentifiers":[{"seriesIdentifiers":[54170986,54170990],"seriesAndModality":[],"studyIdentifier":54103010},{"seriesIdentifiers":[54171019,54171020],"seriesAndModality":[],"studyIdentifier":54103033},{"seriesIdentifiers":[54171954],"seriesAndModality":[],"studyIdentifier":54103706}]},{"subjectId":"217800","project":"NLST","id":54069717,"modalities":["CT"],"bodyParts":["CHEST"],"species":["337915000"],"timepoints":{},"totalNumberOfStudies":2,"totalNumberOfSeries":6,"studyIdentifiers":[{"seriesIdentifiers":[54178377,54178378,63635849],"seriesAndModality":[],"studyIdentifier":54106218},{"seriesIdentifiers":[54181527,54181528,54181529],"seriesAndModality":[],"studyIdentifier":54107387}]},{"subjectId":"217801","project":"NLST","id":54070062,"modalities":["CT"],"bodyParts":["CHEST"],"species":["337915000"],"timepoints":{},"totalNumberOfStudies":3,"totalNumberOfSeries":9,"studyIdentifiers":[{"seriesIdentifiers":[54179580,54179581,63635976],"seriesAndModality":[],"studyIdentifier":54106670},{"seriesIdentifiers":[54180383,54180384,54180385],"seriesAndModality":[],"studyIdentifier":54106961},{"seriesIdentifiers":[54180470,54180471,54180472],"seriesAndModality":[],"studyIdentifier":54106992}]},{"subjectId":"217802","project":"NLST","id":52494653,"modalities":["CT"],"bodyParts":["CHEST"],"species":["337915000"],"timepoints":{},"totalNumberOfStudies":1,"totalNumberOfSeries":2,"studyIdentifiers":[{"seriesIdentifiers":[52560700,52560701],"seriesAndModality":[],"studyIdentifier":52527492}]},{"subjectId":"217803","project":"NLST","id":45810339,"modalities":["CT"],"bodyParts":["CHEST"],"species":["337915000"],"timepoints":{},"totalNumberOfStudies":3,"totalNumberOfSeries":7,"studyIdentifiers":[{"seriesIdentifiers":[45779596,45779597],"seriesAndModality":[],"studyIdentifier":45843584},{"seriesIdentifiers":[72384567,72384568,72384569],"seriesAndModality":[],"studyIdentifier":72351763},{"seriesIdentifiers":[72390937,72391286],"seriesAndModality":[],"studyIdentifier":72354086}]},{"subjectId":"217806","project":"NLST","id":72515943,"modalities":["CT"],"bodyParts":["CHEST"],"species":["337915000"],"timepoints":{},"totalNumberOfStudies":2,"totalNumberOfSeries":7,"studyIdentifiers":[{"seriesIdentifiers":[72386654,72386655,72386656,72386657],"seriesAndModality":[],"studyIdentifier":72352331},{"seriesIdentifiers":[72387819,72387820,72387821],"seriesAndModality":[],"studyIdentifier":72352702}]},{"subjectId":"217808","project":"NLST","id":45810821,"modalities":["CT"],"bodyParts":["CHEST"],"species":["337915000"],"timepoints":{},"totalNumberOfStudies":2,"totalNumberOfSeries":6,"studyIdentifiers":[{"seriesIdentifiers":[45783245,45783246],"seriesAndModality":[],"studyIdentifier":45844951},{"seriesIdentifiers":[52560246,52560247,52560248,52560249],"seriesAndModality":[],"studyIdentifier":52527280}]},{"subjectId":"217809","project":"NLST","id":66290818,"modalities":["CT"],"bodyParts":["CHEST"],"species":["337915000"],"timepoints":{},"totalNumberOfStudies":3,"totalNumberOfSeries":6,"studyIdentifiers":[{"seriesIdentifiers":[66359297,69730594],"seriesAndModality":[],"studyIdentifier":66324412},{"seriesIdentifiers":[66359756,66359757],"seriesAndModality":[],"studyIdentifier":66324675},{"seriesIdentifiers":[66360014,66361051],"seriesAndModality":[],"studyIdentifier":66324817}]},{"subjectId":"217810","project":"NLST","id":54070375,"modalities":["CT"],"bodyParts":["CHEST"],"species":["337915000"],"timepoints":{},"totalNumberOfStudies":3,"totalNumberOfSeries":8,"studyIdentifiers":[{"seriesIdentifiers":[54183088,54183089,54183090],"seriesAndModality":[],"studyIdentifier":54107992},{"seriesIdentifiers":[54184518,54184519],"seriesAndModality":[],"studyIdentifier":54108739},{"seriesIdentifiers":[62259605,62259606,62259607],"seriesAndModality":[],"studyIdentifier":62226587}]},{"subjectId":"217812","project":"NLST","id":54068555,"modalities":["CT"],"bodyParts":["CHEST"],"species":["337915000"],"timepoints":{},"totalNumberOfStudies":3,"totalNumberOfSeries":7,"studyIdentifiers":[{"seriesIdentifiers":[54169315,54169606],"seriesAndModality":[],"studyIdentifier":54102156},{"seriesIdentifiers":[54184909,63636453],"seriesAndModality":[],"studyIdentifier":54108909},{"seriesIdentifiers":[62259719,62259720,62259721],"seriesAndModality":[],"studyIdentifier":62226629}]},{"subjectId":"217813","project":"NLST","id":63995993,"modalities":["CT"],"bodyParts":["CHEST"],"species":["337915000"],"timepoints":{},"totalNumberOfStudies":3,"totalNumberOfSeries":6,"studyIdentifiers":[{"seriesIdentifiers":[63637199,63637200],"seriesAndModality":[],"studyIdentifier":63668466},{"seriesIdentifiers":[63637557,63637558],"seriesAndModality":[],"studyIdentifier":63668638},{"seriesIdentifiers":[72390656,72390657],"seriesAndModality":[],"studyIdentifier":72353927}]},{"subjectId":"217814","project":"NLST","id":54068881,"modalities":["CT"],"bodyParts":["CHEST"],"species":["337915000"],"timepoints":{},"totalNumberOfStudies":3,"totalNumberOfSeries":7,"studyIdentifiers":[{"seriesIdentifiers":[54170826],"seriesAndModality":[],"studyIdentifier":54102874},{"seriesIdentifiers":[54171172,54171173],"seriesAndModality":[],"studyIdentifier":54103144},{"seriesIdentifiers":[54172119,54172120,54172121,54172122],"seriesAndModality":[],"studyIdentifier":54103795}]},{"subjectId":"217824","project":"NLST","id":54069548,"modalities":["CT"],"bodyParts":["CHEST"],"species":["337915000"],"timepoints":{},"totalNumberOfStudies":3,"totalNumberOfSeries":10,"studyIdentifiers":[{"seriesIdentifiers":[54175206,63635585,75956329],"seriesAndModality":[],"studyIdentifier":54105038},{"seriesIdentifiers":[54176100,54176101,54176102],"seriesAndModality":[],"studyIdentifier":54105387},{"seriesIdentifiers":[54177419,54177420,54177421,54177422],"seriesAndModality":[],"studyIdentifier":54105873}]},{"subjectId":"217825","project":"NLST","id":45810885,"modalities":["CT"],"bodyParts":["CHEST"],"species":["337915000"],"timepoints":{},"totalNumberOfStudies":3,"totalNumberOfSeries":12,"studyIdentifiers":[{"seriesIdentifiers":[45783474,45783478,45783479,45783480],"seriesAndModality":[],"studyIdentifier":45845041},{"seriesIdentifiers":[48726505,48726506,48726507,48726508],"seriesAndModality":[],"studyIdentifier":48791671},{"seriesIdentifiers":[48727035,48727681,48727682,48727683],"seriesAndModality":[],"studyIdentifier":48791804}]},{"subjectId":"217830","project":"NLST","id":54067681,"modalities":["CT"],"bodyParts":["CHEST"],"species":["337915000"],"timepoints":{},"totalNumberOfStudies":3,"totalNumberOfSeries":6,"studyIdentifiers":[{"seriesIdentifiers":[54166188,54167619],"seriesAndModality":[],"studyIdentifier":54100509},{"seriesIdentifiers":[63638226,63638227],"seriesAndModality":[],"studyIdentifier":63668947},{"seriesIdentifiers":[63638699,63638700],"seriesAndModality":[],"studyIdentifier":63669126}]},{"subjectId":"217842","project":"NLST","id":66290187,"modalities":["CT"],"bodyParts":["CHEST"],"species":["337915000"],"timepoints":{},"totalNumberOfStudies":3,"totalNumberOfSeries":12,"studyIdentifiers":[{"seriesIdentifiers":[66357018,69730595,69730596,69730597],"seriesAndModality":[],"studyIdentifier":66323160},{"seriesIdentifiers":[69730598,69730599,69730604,69730605],"seriesAndModality":[],"studyIdentifier":69763137},{"seriesIdentifiers":[69731386,69731387,69731391,69731392],"seriesAndModality":[],"studyIdentifier":69763338}]},{"subjectId":"217845","project":"NLST","id":54070683,"modalities":["CT"],"bodyParts":["CHEST"],"species":["337915000"],"timepoints":{},"totalNumberOfStudies":3,"totalNumberOfSeries":8,"studyIdentifiers":[{"seriesIdentifiers":[54184916,54184917],"seriesAndModality":[],"studyIdentifier":54108913},{"seriesIdentifiers":[62259592,62259593,63636523],"seriesAndModality":[],"studyIdentifier":62226582},{"seriesIdentifiers":[62259722,62259723,62259724],"seriesAndModality":[],"studyIdentifier":62226630}]},{"subjectId":"217847","project":"NLST","id":50135318,"modalities":["CT"],"bodyParts":["CHEST"],"species":["337915000"],"timepoints":{},"totalNumberOfStudies":3,"totalNumberOfSeries":12,"studyIdentifiers":[{"seriesIdentifiers":[50201170,50201171,50201179,50202027],"seriesAndModality":[],"studyIdentifier":50168130},{"seriesIdentifiers":[50201334,50201769,50202030,50203503],"seriesAndModality":[],"studyIdentifier":50168194},{"seriesIdentifiers":[50204862,50204898,50204900,50204903],"seriesAndModality":[],"studyIdentifier":50169313}]},{"subjectId":"217851","project":"NLST","id":54069639,"modalities":["CT"],"bodyParts":["CHEST"],"species":["337915000"],"timepoints":{},"totalNumberOfStudies":3,"totalNumberOfSeries":11,"studyIdentifiers":[{"seriesIdentifiers":[54175801,54175802,54175803],"seriesAndModality":[],"studyIdentifier":54105273},{"seriesIdentifiers":[54178034,54178035,54178036,54178037,54178038],"seriesAndModality":[],"studyIdentifier":54106095},{"seriesIdentifiers":[63635477,63635478,63635479],"seriesAndModality":[],"studyIdentifier":63668232}]},{"subjectId":"217856","project":"NLST","id":52494346,"modalities":["CT"],"bodyParts":["CHEST"],"species":["337915000"],"timepoints":{},"totalNumberOfStudies":1,"totalNumberOfSeries":2,"studyIdentifiers":[{"seriesIdentifiers":[52559890,52559891],"seriesAndModality":[],"studyIdentifier":52527114}]},{"subjectId":"217858","project":"NLST","id":52494406,"modalities":["CT"],"bodyParts":["CHEST"],"species":["337915000"],"timepoints":{},"totalNumberOfStudies":1,"totalNumberOfSeries":2,"studyIdentifiers":[{"seriesIdentifiers":[52560039,52560040],"seriesAndModality":[],"studyIdentifier":52527187}]},{"subjectId":"217860","project":"NLST","id":48758832,"modalities":["CT"],"bodyParts":["CHEST"],"species":["337915000"],"timepoints":{},"totalNumberOfStudies":3,"totalNumberOfSeries":12,"studyIdentifiers":[{"seriesIdentifiers":[48726225,48726233,48726234,48726235],"seriesAndModality":[],"studyIdentifier":48791602},{"seriesIdentifiers":[48726998,48726999,48727000,48727001],"seriesAndModality":[],"studyIdentifier":48791794},{"seriesIdentifiers":[48727786,48728143,48728144,48728145],"seriesAndModality":[],"studyIdentifier":48792056}]},{"subjectId":"217862","project":"NLST","id":52494614,"modalities":["CT"],"bodyParts":["CHEST"],"species":["337915000"],"timepoints":{},"totalNumberOfStudies":1,"totalNumberOfSeries":2,"studyIdentifiers":[{"seriesIdentifiers":[52560611,52560612],"seriesAndModality":[],"studyIdentifier":52527450}]},{"subjectId":"217864","project":"NLST","id":54067603,"modalities":["CT"],"bodyParts":["CHEST"],"species":["337915000"],"timepoints":{},"totalNumberOfStudies":3,"totalNumberOfSeries":6,"studyIdentifiers":[{"seriesIdentifiers":[54166050,54166091],"seriesAndModality":[],"studyIdentifier":54100412},{"seriesIdentifiers":[63638267,63638268],"seriesAndModality":[],"studyIdentifier":63668968},{"seriesIdentifiers":[63638778,63638779],"seriesAndModality":[],"studyIdentifier":63669146}]},{"subjectId":"217865","project":"NLST","id":54067323,"modalities":["CT"],"bodyParts":["CHEST"],"species":["337915000"],"timepoints":{},"totalNumberOfStudies":3,"totalNumberOfSeries":5,"studyIdentifiers":[{"seriesIdentifiers":[54165648,54169554],"seriesAndModality":[],"studyIdentifier":54100096},{"seriesIdentifiers":[54167209],"seriesAndModality":[],"studyIdentifier":54101216},{"seriesIdentifiers":[54169285,54169286],"seriesAndModality":[],"studyIdentifier":54102141}]}],"totalPatients":25970,"bodyParts":[{"value":"CHEST","count":25970}],"modalities":[{"value":"CT","count":25970}],"collections":[{"value":"NLST","count":25970}],"species":[{"value":"337915000","count":25970}],"maxTimepoints":{},"minTimepoints":{},"sort":"subject-ascending"}