[{"studyId":"1.2.840.113654.2.55.150563384232394521946871342754479176327","date":946792800000,"description":"NLST-LSS","id":9767531,"study_id":null,"excludeCommercial":null,"seriesList":[{"seriesNumber":"2","seriesUID":"1.2.840.113654.2.55.181674239102580616543848552596335609229","numberImages":138,"modality":"CT","manufacturer":"GE MEDICAL SYSTEMS","annotationsFlag":false,"annotationsSize":0,"patientId":"121647","patientPkId":"6358277","studyId":"1.2.840.113654.2.55.150563384232394521946871342754479176327","studyPkId":9767531,"totalSizeForAllImagesInSeries":72668882,"project":"NLST","description":"1,OPA,GE,LS16,B,330,2.5,120,60.0,0.1,1.375","dataProvenanceSiteName":null,"manufacturerModelName":null,"softwareVersion":null,"maxFrameCount":"0","studyDate":null,"studyDesc":null,"bodyPartExamined":"CHEST","study_id":null,"thirdPartyAnalysis":null,"descriptionURI":null,"sopClassUID":null,"licenseName":null,"licenseUrl":null,"commercialRestrictions":false,"seriesId":"1.2.840.113654.2.55.181674239102580616543848552596335609229","studyDateString":"","exactSize":72668882,"seriesPkId":9738176}]}]