[{"studyId":"1.3.6.1.4.1.14519.5.2.1.7009.9004.270888300905854743853535167791","date":978415200000,"description":"NLST-ACRIN","id":50169952,"study_id":null,"excludeCommercial":null,"seriesList":[{"seriesNumber":"2","seriesUID":"1.3.6.1.4.1.14519.5.2.1.7009.9004.254862714331306884379151232317","numberImages":182,"modality":"CT","manufacturer":"SIEMENS","annotationsFlag":false,"annotationsSize":0,"patientId":"205944","patientPkId":"50135833","studyId":"1.3.6.1.4.1.14519.5.2.1.7009.9004.270888300905854743853535167791","studyPkId":50169952,"totalSizeForAllImagesInSeries":95866036,"project":"NLST","description":"2,OPA,SE,SEN64,B30f,320,2,120,25,25,1","dataProvenanceSiteName":null,"manufacturerModelName":null,"softwareVersion":null,"maxFrameCount":"0","studyDate":null,"studyDesc":null,"bodyPartExamined":"CHEST","study_id":null,"thirdPartyAnalysis":null,"descriptionURI":null,"sopClassUID":null,"licenseName":null,"licenseUrl":null,"commercialRestrictions":false,"seriesId":"1.3.6.1.4.1.14519.5.2.1.7009.9004.254862714331306884379151232317","studyDateString":"","exactSize":95866036,"seriesPkId":50205937}]}]