[{"studyId":"1.3.6.1.4.1.14519.5.2.1.7009.9004.121880157994574932521649885373","date":978415200000,"description":"NLST-ACRIN","id":62227122,"study_id":null,"excludeCommercial":null,"seriesList":[{"seriesNumber":"2","seriesUID":"1.3.6.1.4.1.14519.5.2.1.7009.9004.183158265477541046253905460160","numberImages":149,"modality":"CT","manufacturer":"GE MEDICAL SYSTEMS","annotationsFlag":false,"annotationsSize":0,"patientId":"210068","patientPkId":"54067495","studyId":"1.3.6.1.4.1.14519.5.2.1.7009.9004.121880157994574932521649885373","studyPkId":62227122,"totalSizeForAllImagesInSeries":78547006,"project":"NLST","description":"2,OPA,GE,LSQX,STANDARD,320,2.5,120,40,26.7,1.5","dataProvenanceSiteName":null,"manufacturerModelName":null,"softwareVersion":null,"maxFrameCount":"0","studyDate":null,"studyDesc":null,"bodyPartExamined":"CHEST","study_id":null,"thirdPartyAnalysis":null,"descriptionURI":null,"sopClassUID":null,"licenseName":null,"licenseUrl":null,"commercialRestrictions":false,"seriesId":"1.3.6.1.4.1.14519.5.2.1.7009.9004.183158265477541046253905460160","studyDateString":"","exactSize":78547006,"seriesPkId":62261317}]}]